{"data": [{"projectId": null, "endsAt": "2017-12-29T02:13:40.965Z", "bidGroupId": 46776, "amount": "4773", "bidIndex": 0, "address": "0x38001a6ab8d70bab89333d9e945c847cbeb8c477", "y": 133, "x": 30, "updatedAt": "2017-12-27T20:13:40.994Z", "id": "30,133", "createdAt": "2017-12-15T22:00:53.577Z"}, {"projectId": "faba40bd-21bc-4321-93e6-3e38bce32ea8", "endsAt": null, "bidGroupId": null, "amount": null, "bidIndex": null, "address": null, "y": 133, "x": -35, "updatedAt": "2017-12-15T22:04:07.987Z", "id": "-35,133", "createdAt": "2017-12-15T22:00:00.985Z"}, {"projectId": "faba40bd-21bc-4321-93e6-3e38bce32ea8", "endsAt": null, "bidGroupId": null, "amount": null, "bidIndex": null, "address": null, "y": 133, "x": -34, "updatedAt": "2017-12-15T22:04:07.990Z", "id": "-34,133", "createdAt": "2017-12-15T22:00:01.787Z"}, {"projectId": "faba40bd-21bc-4321-93e6-3e38bce32ea8", "endsAt": null, "bidGroupId": null, "amount": null, "bidIndex": null, "address": null, "y": 133, "x": -33, "updatedAt": "2017-12-15T22:04:07.994Z", "id": "-33,133", "createdAt": "2017-12-15T22:00:02.634Z"}, {"projectId": "faba40bd-21bc-4321-93e6-3e38bce32ea8", "endsAt": null, "bidGroupId": null, "amount": null, "bidIndex": null, "address": null, "y": 133, "x": -32, "updatedAt": "2017-12-15T22:04:07.997Z", "id": "-32,133", "createdAt": "2017-12-15T22:00:03.434Z"}, {"projectId": "faba40bd-21bc-4321-93e6-3e38bce32ea8", "endsAt": null, "bidGroupId": null, "amount": null, "bidIndex": null, "address": null, "y": 133, "x": -31, "updatedAt": "2017-12-15T22:04:08.004Z", "id": "-31,133", "createdAt": "2017-12-15T22:00:04.250Z"}, {"projectId": "faba40bd-21bc-4321-93e6-3e38bce32ea8", "endsAt": null, "bidGroupId": null, "amount": null, "bidIndex": null, "address": null, "y": 133, "x": -30, "updatedAt": "2017-12-15T22:04:08.011Z", "id": "-30,133", "createdAt": "2017-12-15T22:00:05.024Z"}, {"projectId": "faba40bd-21bc-4321-93e6-3e38bce32ea8", "endsAt": null, "bidGroupId": null, "amount": null, "bidIndex": null, "address": null, "y": 133, "x": -29, "updatedAt": "2017-12-15T22:04:08.016Z", "id": "-29,133", "createdAt": "2017-12-15T22:00:05.799Z"}, {"projectId": "faba40bd-21bc-4321-93e6-3e38bce32ea8", "endsAt": null, "bidGroupId": null, "amount": null, "bidIndex": null, "address": null, "y": 133, "x": -28, "updatedAt": "2017-12-15T22:04:08.020Z", "id": "-28,133", "createdAt": "2017-12-15T22:00:06.563Z"}, {"projectId": "faba40bd-21bc-4321-93e6-3e38bce32ea8", "endsAt": null, "bidGroupId": null, "amount": null, "bidIndex": null, "address": null, "y": 133, "x": -27, "updatedAt": "2017-12-15T22:04:08.023Z", "id": "-27,133", "createdAt": "2017-12-15T22:00:07.309Z"}, {"projectId": "faba40bd-21bc-4321-93e6-3e38bce32ea8", "endsAt": null, "bidGroupId": null, "amount": null, "bidIndex": null, "address": null, "y": 133, "x": -26, "updatedAt": "2017-12-15T22:04:08.028Z", "id": "-26,133", "createdAt": "2017-12-15T22:00:08.140Z"}, {"projectId": "faba40bd-21bc-4321-93e6-3e38bce32ea8", "endsAt": null, "bidGroupId": null, "amount": null, "bidIndex": null, "address": null, "y": 133, "x": -25, "updatedAt": "2017-12-15T22:04:08.033Z", "id": "-25,133", "createdAt": "2017-12-15T22:00:08.926Z"}, {"projectId": "faba40bd-21bc-4321-93e6-3e38bce32ea8", "endsAt": null, "bidGroupId": null, "amount": null, "bidIndex": null, "address": null, "y": 133, "x": -24, "updatedAt": "2017-12-15T22:04:08.036Z", "id": "-24,133", "createdAt": "2017-12-15T22:00:09.759Z"}, {"projectId": "faba40bd-21bc-4321-93e6-3e38bce32ea8", "endsAt": null, "bidGroupId": null, "amount": null, "bidIndex": null, "address": null, "y": 133, "x": -23, "updatedAt": "2017-12-15T22:04:08.039Z", "id": "-23,133", "createdAt": "2017-12-15T22:00:10.569Z"}, {"projectId": "faba40bd-21bc-4321-93e6-3e38bce32ea8", "endsAt": null, "bidGroupId": null, "amount": null, "bidIndex": null, "address": null, "y": 133, "x": -22, "updatedAt": "2017-12-15T22:04:08.042Z", "id": "-22,133", "createdAt": "2017-12-15T22:00:11.363Z"}, {"projectId": "faba40bd-21bc-4321-93e6-3e38bce32ea8", "endsAt": null, "bidGroupId": null, "amount": null, "bidIndex": null, "address": null, "y": 133, "x": -21, "updatedAt": "2017-12-15T22:04:08.046Z", "id": "-21,133", "createdAt": "2017-12-15T22:00:12.218Z"}, {"projectId": "faba40bd-21bc-4321-93e6-3e38bce32ea8", "endsAt": null, "bidGroupId": null, "amount": null, "bidIndex": null, "address": null, "y": 133, "x": -20, "updatedAt": "2017-12-15T22:04:08.049Z", "id": "-20,133", "createdAt": "2017-12-15T22:00:13.021Z"}, {"projectId": "faba40bd-21bc-4321-93e6-3e38bce32ea8", "endsAt": null, "bidGroupId": null, "amount": null, "bidIndex": null, "address": null, "y": 133, "x": -19, "updatedAt": "2017-12-15T22:04:08.051Z", "id": "-19,133", "createdAt": "2017-12-15T22:00:13.788Z"}, {"projectId": "faba40bd-21bc-4321-93e6-3e38bce32ea8", "endsAt": null, "bidGroupId": null, "amount": null, "bidIndex": null, "address": null, "y": 133, "x": -18, "updatedAt": "2017-12-15T22:04:08.054Z", "id": "-18,133", "createdAt": "2017-12-15T22:00:14.576Z"}, {"projectId": "faba40bd-21bc-4321-93e6-3e38bce32ea8", "endsAt": null, "bidGroupId": null, "amount": null, "bidIndex": null, "address": null, "y": 133, "x": -17, "updatedAt": "2017-12-15T22:04:08.057Z", "id": "-17,133", "createdAt": "2017-12-15T22:00:15.383Z"}, {"projectId": "faba40bd-21bc-4321-93e6-3e38bce32ea8", "endsAt": null, "bidGroupId": null, "amount": null, "bidIndex": null, "address": null, "y": 133, "x": -16, "updatedAt": "2017-12-15T22:04:08.060Z", "id": "-16,133", "createdAt": "2017-12-15T22:00:16.188Z"}, {"projectId": "faba40bd-21bc-4321-93e6-3e38bce32ea8", "endsAt": null, "bidGroupId": null, "amount": null, "bidIndex": null, "address": null, "y": 133, "x": -15, "updatedAt": "2017-12-15T22:04:08.063Z", "id": "-15,133", "createdAt": "2017-12-15T22:00:16.997Z"}, {"projectId": "faba40bd-21bc-4321-93e6-3e38bce32ea8", "endsAt": null, "bidGroupId": null, "amount": null, "bidIndex": null, "address": null, "y": 133, "x": -14, "updatedAt": "2017-12-15T22:04:08.066Z", "id": "-14,133", "createdAt": "2017-12-15T22:00:17.835Z"}, {"projectId": "faba40bd-21bc-4321-93e6-3e38bce32ea8", "endsAt": null, "bidGroupId": null, "amount": null, "bidIndex": null, "address": null, "y": 133, "x": -13, "updatedAt": "2017-12-15T22:04:08.068Z", "id": "-13,133", "createdAt": "2017-12-15T22:00:18.656Z"}, {"projectId": "faba40bd-21bc-4321-93e6-3e38bce32ea8", "endsAt": null, "bidGroupId": null, "amount": null, "bidIndex": null, "address": null, "y": 133, "x": -12, "updatedAt": "2017-12-15T22:04:08.071Z", "id": "-12,133", "createdAt": "2017-12-15T22:00:19.504Z"}, {"projectId": "faba40bd-21bc-4321-93e6-3e38bce32ea8", "endsAt": null, "bidGroupId": null, "amount": null, "bidIndex": null, "address": null, "y": 133, "x": -11, "updatedAt": "2017-12-15T22:04:08.074Z", "id": "-11,133", "createdAt": "2017-12-15T22:00:20.342Z"}, {"projectId": "faba40bd-21bc-4321-93e6-3e38bce32ea8", "endsAt": null, "bidGroupId": null, "amount": null, "bidIndex": null, "address": null, "y": 133, "x": -10, "updatedAt": "2017-12-15T22:04:08.076Z", "id": "-10,133", "createdAt": "2017-12-15T22:00:21.097Z"}, {"projectId": "faba40bd-21bc-4321-93e6-3e38bce32ea8", "endsAt": null, "bidGroupId": null, "amount": null, "bidIndex": null, "address": null, "y": 133, "x": -9, "updatedAt": "2017-12-15T22:04:08.079Z", "id": "-9,133", "createdAt": "2017-12-15T22:00:21.904Z"}, {"projectId": "faba40bd-21bc-4321-93e6-3e38bce32ea8", "endsAt": null, "bidGroupId": null, "amount": null, "bidIndex": null, "address": null, "y": 133, "x": -8, "updatedAt": "2017-12-15T22:04:08.082Z", "id": "-8,133", "createdAt": "2017-12-15T22:00:22.684Z"}, {"projectId": "faba40bd-21bc-4321-93e6-3e38bce32ea8", "endsAt": null, "bidGroupId": null, "amount": null, "bidIndex": null, "address": null, "y": 133, "x": -7, "updatedAt": "2017-12-15T22:04:08.084Z", "id": "-7,133", "createdAt": "2017-12-15T22:00:23.510Z"}, {"projectId": "faba40bd-21bc-4321-93e6-3e38bce32ea8", "endsAt": null, "bidGroupId": null, "amount": null, "bidIndex": null, "address": null, "y": 133, "x": -6, "updatedAt": "2017-12-15T22:04:08.087Z", "id": "-6,133", "createdAt": "2017-12-15T22:00:24.335Z"}, {"projectId": "faba40bd-21bc-4321-93e6-3e38bce32ea8", "endsAt": null, "bidGroupId": null, "amount": null, "bidIndex": null, "address": null, "y": 133, "x": -5, "updatedAt": "2017-12-15T22:04:08.090Z", "id": "-5,133", "createdAt": "2017-12-15T22:00:25.136Z"}, {"projectId": "faba40bd-21bc-4321-93e6-3e38bce32ea8", "endsAt": null, "bidGroupId": null, "amount": null, "bidIndex": null, "address": null, "y": 133, "x": -4, "updatedAt": "2017-12-15T22:04:08.092Z", "id": "-4,133", "createdAt": "2017-12-15T22:00:25.943Z"}, {"projectId": "faba40bd-21bc-4321-93e6-3e38bce32ea8", "endsAt": null, "bidGroupId": null, "amount": null, "bidIndex": null, "address": null, "y": 133, "x": -3, "updatedAt": "2017-12-15T22:04:08.095Z", "id": "-3,133", "createdAt": "2017-12-15T22:00:26.745Z"}, {"projectId": "faba40bd-21bc-4321-93e6-3e38bce32ea8", "endsAt": null, "bidGroupId": null, "amount": null, "bidIndex": null, "address": null, "y": 133, "x": -2, "updatedAt": "2017-12-15T22:04:08.099Z", "id": "-2,133", "createdAt": "2017-12-15T22:00:27.573Z"}, {"projectId": "faba40bd-21bc-4321-93e6-3e38bce32ea8", "endsAt": null, "bidGroupId": null, "amount": null, "bidIndex": null, "address": null, "y": 133, "x": -1, "updatedAt": "2017-12-15T22:04:08.102Z", "id": "-1,133", "createdAt": "2017-12-15T22:00:28.393Z"}, {"projectId": "faba40bd-21bc-4321-93e6-3e38bce32ea8", "endsAt": null, "bidGroupId": null, "amount": null, "bidIndex": null, "address": null, "y": 133, "x": 0, "updatedAt": "2017-12-15T22:04:08.104Z", "id": "0,133", "createdAt": "2017-12-15T22:00:29.177Z"}, {"projectId": null, "endsAt": "2017-12-22T22:00:00.000Z", "bidGroupId": 16068, "amount": "1000", "bidIndex": 3, "address": "0xb522bd8a501dfa970c40b57eb76c76256d55758d", "y": 133, "x": -64, "updatedAt": "2017-12-20T04:31:02.282Z", "id": "-64,133", "createdAt": "2017-12-15T21:59:37.205Z"}, {"projectId": null, "endsAt": "2017-12-22T22:00:00.000Z", "bidGroupId": 16068, "amount": "1000", "bidIndex": 7, "address": "0xb522bd8a501dfa970c40b57eb76c76256d55758d", "y": 133, "x": -62, "updatedAt": "2017-12-20T04:31:02.284Z", "id": "-62,133", "createdAt": "2017-12-15T21:59:38.867Z"}, {"projectId": null, "endsAt": "2017-12-22T22:00:00.000Z", "bidGroupId": 16068, "amount": "1000", "bidIndex": 11, "address": "0xb522bd8a501dfa970c40b57eb76c76256d55758d", "y": 133, "x": -60, "updatedAt": "2017-12-20T04:31:02.287Z", "id": "-60,133", "createdAt": "2017-12-15T21:59:40.494Z"}, {"projectId": "219ac351-e6ce-4e17-8b84-eb008afddf69", "endsAt": null, "bidGroupId": null, "amount": null, "bidIndex": null, "address": null, "y": 133, "x": 78, "updatedAt": "2017-12-15T22:03:03.985Z", "id": "78,133", "createdAt": "2017-12-15T22:01:32.141Z"}, {"projectId": "219ac351-e6ce-4e17-8b84-eb008afddf69", "endsAt": null, "bidGroupId": null, "amount": null, "bidIndex": null, "address": null, "y": 133, "x": 80, "updatedAt": "2017-12-15T22:03:03.990Z", "id": "80,133", "createdAt": "2017-12-15T22:01:33.754Z"}, {"projectId": "219ac351-e6ce-4e17-8b84-eb008afddf69", "endsAt": null, "bidGroupId": null, "amount": null, "bidIndex": null, "address": null, "y": 133, "x": 82, "updatedAt": "2017-12-15T22:03:03.995Z", "id": "82,133", "createdAt": "2017-12-15T22:01:35.348Z"}, {"projectId": "219ac351-e6ce-4e17-8b84-eb008afddf69", "endsAt": null, "bidGroupId": null, "amount": null, "bidIndex": null, "address": null, "y": 133, "x": 84, "updatedAt": "2017-12-15T22:03:04.002Z", "id": "84,133", "createdAt": "2017-12-15T22:01:36.969Z"}, {"projectId": "219ac351-e6ce-4e17-8b84-eb008afddf69", "endsAt": null, "bidGroupId": null, "amount": null, "bidIndex": null, "address": null, "y": 133, "x": 86, "updatedAt": "2017-12-15T22:03:04.013Z", "id": "86,133", "createdAt": "2017-12-15T22:01:38.562Z"}, {"projectId": "219ac351-e6ce-4e17-8b84-eb008afddf69", "endsAt": null, "bidGroupId": null, "amount": null, "bidIndex": null, "address": null, "y": 133, "x": 88, "updatedAt": "2017-12-15T22:03:04.020Z", "id": "88,133", "createdAt": "2017-12-15T22:01:40.172Z"}, {"projectId": "219ac351-e6ce-4e17-8b84-eb008afddf69", "endsAt": null, "bidGroupId": null, "amount": null, "bidIndex": null, "address": null, "y": 133, "x": 105, "updatedAt": "2017-12-15T22:03:04.065Z", "id": "105,133", "createdAt": "2017-12-15T22:01:53.912Z"}, {"projectId": "219ac351-e6ce-4e17-8b84-eb008afddf69", "endsAt": null, "bidGroupId": null, "amount": null, "bidIndex": null, "address": null, "y": 133, "x": 112, "updatedAt": "2017-12-15T22:03:04.081Z", "id": "112,133", "createdAt": "2017-12-15T22:01:59.523Z"}, {"projectId": "219ac351-e6ce-4e17-8b84-eb008afddf69", "endsAt": null, "bidGroupId": null, "amount": null, "bidIndex": null, "address": null, "y": 133, "x": 121, "updatedAt": "2017-12-15T22:03:04.101Z", "id": "121,133", "createdAt": "2017-12-15T22:02:06.800Z"}, {"projectId": "219ac351-e6ce-4e17-8b84-eb008afddf69", "endsAt": null, "bidGroupId": null, "amount": null, "bidIndex": null, "address": null, "y": 133, "x": 130, "updatedAt": "2017-12-15T22:03:04.121Z", "id": "130,133", "createdAt": "2017-12-15T22:02:14.089Z"}, {"projectId": "219ac351-e6ce-4e17-8b84-eb008afddf69", "endsAt": null, "bidGroupId": null, "amount": null, "bidIndex": null, "address": null, "y": 133, "x": 137, "updatedAt": "2017-12-15T22:03:04.138Z", "id": "137,133", "createdAt": "2017-12-15T22:02:19.738Z"}, {"projectId": "219ac351-e6ce-4e17-8b84-eb008afddf69", "endsAt": null, "bidGroupId": null, "amount": null, "bidIndex": null, "address": null, "y": 133, "x": 146, "updatedAt": "2017-12-15T22:03:04.158Z", "id": "146,133", "createdAt": "2017-12-15T22:02:26.912Z"}, {"projectId": null, "endsAt": "2017-12-22T22:00:00.000Z", "bidGroupId": 16068, "amount": "1000", "bidIndex": 0, "address": "0xb522bd8a501dfa970c40b57eb76c76256d55758d", "y": 133, "x": -65, "updatedAt": "2017-12-20T04:31:02.280Z", "id": "-65,133", "createdAt": "2017-12-15T21:59:36.376Z"}, {"projectId": null, "endsAt": "2017-12-22T22:00:00.000Z", "bidGroupId": 16068, "amount": "1000", "bidIndex": 4, "address": "0xb522bd8a501dfa970c40b57eb76c76256d55758d", "y": 133, "x": -63, "updatedAt": "2017-12-20T04:31:02.282Z", "id": "-63,133", "createdAt": "2017-12-15T21:59:38.028Z"}, {"projectId": null, "endsAt": "2017-12-22T22:00:00.000Z", "bidGroupId": 16068, "amount": "1000", "bidIndex": 8, "address": "0xb522bd8a501dfa970c40b57eb76c76256d55758d", "y": 133, "x": -61, "updatedAt": "2017-12-20T04:31:02.285Z", "id": "-61,133", "createdAt": "2017-12-15T21:59:39.682Z"}, {"projectId": null, "endsAt": "2017-12-22T22:00:00.000Z", "bidGroupId": 16068, "amount": "1000", "bidIndex": 12, "address": "0xb522bd8a501dfa970c40b57eb76c76256d55758d", "y": 133, "x": -59, "updatedAt": "2017-12-20T04:31:02.288Z", "id": "-59,133", "createdAt": "2017-12-15T21:59:41.297Z"}, {"projectId": null, "endsAt": "2017-12-22T22:00:00.000Z", "bidGroupId": 18181, "amount": "1000", "bidIndex": 3, "address": "0xb522bd8a501dfa970c40b57eb76c76256d55758d", "y": 133, "x": -58, "updatedAt": "2017-12-20T20:09:36.344Z", "id": "-58,133", "createdAt": "2017-12-15T21:59:42.135Z"}, {"projectId": null, "endsAt": "2017-12-26T16:42:21.418Z", "bidGroupId": 43228, "amount": "2443", "bidIndex": 0, "address": "0xc1ab891ca2d7a85e0f2156bd8d2b5de0666d057b", "y": 133, "x": -56, "updatedAt": "2017-12-25T10:42:21.425Z", "id": "-56,133", "createdAt": "2017-12-15T21:59:43.764Z"}, {"projectId": null, "endsAt": "2017-12-30T01:15:12.046Z", "bidGroupId": 47275, "amount": "6100", "bidIndex": 1, "address": "0xccd5089557ae6a2ba063e8720e725a6bf743b3e8", "y": 133, "x": -42, "updatedAt": "2017-12-28T19:15:12.059Z", "id": "-42,133", "createdAt": "2017-12-15T21:59:55.188Z"}, {"projectId": "f77140f9-c7b4-4787-89c9-9fa0e219b079", "endsAt": null, "bidGroupId": null, "amount": null, "bidIndex": null, "address": null, "y": 133, "x": 3, "updatedAt": "2017-12-15T22:04:14.746Z", "id": "3,133", "createdAt": "2017-12-15T22:00:31.662Z"}, {"projectId": "f77140f9-c7b4-4787-89c9-9fa0e219b079", "endsAt": null, "bidGroupId": null, "amount": null, "bidIndex": null, "address": null, "y": 133, "x": 5, "updatedAt": "2017-12-15T22:04:14.751Z", "id": "5,133", "createdAt": "2017-12-15T22:00:33.272Z"}, {"projectId": "f77140f9-c7b4-4787-89c9-9fa0e219b079", "endsAt": null, "bidGroupId": null, "amount": null, "bidIndex": null, "address": null, "y": 133, "x": 7, "updatedAt": "2017-12-15T22:04:14.755Z", "id": "7,133", "createdAt": "2017-12-15T22:00:34.938Z"}, {"projectId": "f77140f9-c7b4-4787-89c9-9fa0e219b079", "endsAt": null, "bidGroupId": null, "amount": null, "bidIndex": null, "address": null, "y": 133, "x": 9, "updatedAt": "2017-12-15T22:04:14.760Z", "id": "9,133", "createdAt": "2017-12-15T22:00:36.519Z"}, {"projectId": "f77140f9-c7b4-4787-89c9-9fa0e219b079", "endsAt": null, "bidGroupId": null, "amount": null, "bidIndex": null, "address": null, "y": 133, "x": 11, "updatedAt": "2017-12-15T22:04:14.766Z", "id": "11,133", "createdAt": "2017-12-15T22:00:38.151Z"}, {"projectId": "f77140f9-c7b4-4787-89c9-9fa0e219b079", "endsAt": null, "bidGroupId": null, "amount": null, "bidIndex": null, "address": null, "y": 133, "x": 13, "updatedAt": "2017-12-15T22:04:14.771Z", "id": "13,133", "createdAt": "2017-12-15T22:00:39.737Z"}, {"projectId": null, "endsAt": "2017-12-26T07:50:41.012Z", "bidGroupId": 42176, "amount": "2657", "bidIndex": 0, "address": "0xccd5089557ae6a2ba063e8720e725a6bf743b3e8", "y": 133, "x": -43, "updatedAt": "2017-12-25T01:50:41.028Z", "id": "-43,133", "createdAt": "2017-12-15T21:59:54.389Z"}, {"projectId": "f77140f9-c7b4-4787-89c9-9fa0e219b079", "endsAt": null, "bidGroupId": null, "amount": null, "bidIndex": null, "address": null, "y": 133, "x": 15, "updatedAt": "2017-12-15T22:04:14.776Z", "id": "15,133", "createdAt": "2017-12-15T22:00:41.392Z"}, {"projectId": null, "endsAt": "2017-12-22T22:00:00.000Z", "bidGroupId": 11901, "amount": "1000", "bidIndex": 7, "address": "0x0069e55468bf889925a7a85e8a1945fbc75267f5", "y": 133, "x": 38, "updatedAt": "2017-12-17T11:21:45.971Z", "id": "38,133", "createdAt": "2017-12-15T22:00:59.937Z"}, {"projectId": null, "endsAt": "2017-12-29T11:23:52.748Z", "bidGroupId": 47018, "amount": "5967", "bidIndex": 0, "address": "0xb096e691b197e4622bc0033a2efda76082b33783", "y": 133, "x": 36, "updatedAt": "2017-12-28T05:23:52.755Z", "id": "36,133", "createdAt": "2017-12-15T22:00:58.383Z"}, {"projectId": null, "endsAt": "2017-12-26T11:06:29.210Z", "bidGroupId": 42596, "amount": "3750", "bidIndex": 0, "address": "0xccd5089557ae6a2ba063e8720e725a6bf743b3e8", "y": 133, "x": -45, "updatedAt": "2017-12-25T05:06:29.218Z", "id": "-45,133", "createdAt": "2017-12-15T21:59:52.763Z"}, {"projectId": null, "endsAt": "2017-12-22T22:00:00.000Z", "bidGroupId": 11901, "amount": "1000", "bidIndex": 4, "address": "0x0069e55468bf889925a7a85e8a1945fbc75267f5", "y": 133, "x": 37, "updatedAt": "2017-12-17T11:21:45.968Z", "id": "37,133", "createdAt": "2017-12-15T22:00:59.172Z"}, {"projectId": null, "endsAt": null, "bidGroupId": null, "amount": null, "bidIndex": null, "address": null, "y": 133, "x": 39, "updatedAt": "2017-12-15T22:01:00.824Z", "id": "39,133", "createdAt": "2017-12-15T22:01:00.824Z"}, {"projectId": null, "endsAt": null, "bidGroupId": null, "amount": null, "bidIndex": null, "address": null, "y": 133, "x": 40, "updatedAt": "2017-12-15T22:01:01.697Z", "id": "40,133", "createdAt": "2017-12-15T22:01:01.697Z"}, {"projectId": null, "endsAt": null, "bidGroupId": null, "amount": null, "bidIndex": null, "address": null, "y": 133, "x": 41, "updatedAt": "2017-12-15T22:01:02.500Z", "id": "41,133", "createdAt": "2017-12-15T22:01:02.500Z"}, {"projectId": null, "endsAt": null, "bidGroupId": null, "amount": null, "bidIndex": null, "address": null, "y": 133, "x": 42, "updatedAt": "2017-12-15T22:01:03.270Z", "id": "42,133", "createdAt": "2017-12-15T22:01:03.270Z"}, {"projectId": null, "endsAt": null, "bidGroupId": null, "amount": null, "bidIndex": null, "address": null, "y": 133, "x": 43, "updatedAt": "2017-12-15T22:01:04.086Z", "id": "43,133", "createdAt": "2017-12-15T22:01:04.086Z"}, {"projectId": null, "endsAt": null, "bidGroupId": null, "amount": null, "bidIndex": null, "address": null, "y": 133, "x": 44, "updatedAt": "2017-12-15T22:01:04.870Z", "id": "44,133", "createdAt": "2017-12-15T22:01:04.870Z"}, {"projectId": null, "endsAt": null, "bidGroupId": null, "amount": null, "bidIndex": null, "address": null, "y": 133, "x": 45, "updatedAt": "2017-12-15T22:01:05.660Z", "id": "45,133", "createdAt": "2017-12-15T22:01:05.660Z"}, {"projectId": null, "endsAt": null, "bidGroupId": null, "amount": null, "bidIndex": null, "address": null, "y": 133, "x": 46, "updatedAt": "2017-12-15T22:01:06.480Z", "id": "46,133", "createdAt": "2017-12-15T22:01:06.480Z"}, {"projectId": null, "endsAt": null, "bidGroupId": null, "amount": null, "bidIndex": null, "address": null, "y": 133, "x": 47, "updatedAt": "2017-12-15T22:01:07.264Z", "id": "47,133", "createdAt": "2017-12-15T22:01:07.264Z"}, {"projectId": null, "endsAt": "2017-12-22T22:00:00.000Z", "bidGroupId": 12415, "amount": "1000", "bidIndex": 0, "address": "0x6c0b585429fa0cd9dbf6d87bb3e51dac85f42635", "y": 133, "x": 48, "updatedAt": "2017-12-17T15:35:24.592Z", "id": "48,133", "createdAt": "2017-12-15T22:01:08.043Z"}, {"projectId": null, "endsAt": "2017-12-22T22:00:00.000Z", "bidGroupId": 7499, "amount": "1250", "bidIndex": 0, "address": "0x521b0fef9cdcf250abaf8e7bc798cbe13fa98692", "y": 133, "x": 49, "updatedAt": "2017-12-16T11:36:26.649Z", "id": "49,133", "createdAt": "2017-12-15T22:01:08.811Z"}, {"projectId": null, "endsAt": "2017-12-22T22:00:00.000Z", "bidGroupId": 7499, "amount": "1250", "bidIndex": 1, "address": "0x521b0fef9cdcf250abaf8e7bc798cbe13fa98692", "y": 133, "x": 50, "updatedAt": "2017-12-16T11:36:26.652Z", "id": "50,133", "createdAt": "2017-12-15T22:01:09.604Z"}, {"projectId": "219ac351-e6ce-4e17-8b84-eb008afddf69", "endsAt": null, "bidGroupId": null, "amount": null, "bidIndex": null, "address": null, "y": 133, "x": 62, "updatedAt": "2017-12-15T22:03:03.950Z", "id": "62,133", "createdAt": "2017-12-15T22:01:19.274Z"}, {"projectId": "219ac351-e6ce-4e17-8b84-eb008afddf69", "endsAt": null, "bidGroupId": null, "amount": null, "bidIndex": null, "address": null, "y": 133, "x": 63, "updatedAt": "2017-12-15T22:03:03.952Z", "id": "63,133", "createdAt": "2017-12-15T22:01:20.101Z"}, {"projectId": "219ac351-e6ce-4e17-8b84-eb008afddf69", "endsAt": null, "bidGroupId": null, "amount": null, "bidIndex": null, "address": null, "y": 133, "x": 64, "updatedAt": "2017-12-15T22:03:03.954Z", "id": "64,133", "createdAt": "2017-12-15T22:01:20.909Z"}, {"projectId": "219ac351-e6ce-4e17-8b84-eb008afddf69", "endsAt": null, "bidGroupId": null, "amount": null, "bidIndex": null, "address": null, "y": 133, "x": 65, "updatedAt": "2017-12-15T22:03:03.957Z", "id": "65,133", "createdAt": "2017-12-15T22:01:21.774Z"}, {"projectId": "219ac351-e6ce-4e17-8b84-eb008afddf69", "endsAt": null, "bidGroupId": null, "amount": null, "bidIndex": null, "address": null, "y": 133, "x": 66, "updatedAt": "2017-12-15T22:03:03.959Z", "id": "66,133", "createdAt": "2017-12-15T22:01:22.547Z"}, {"projectId": "219ac351-e6ce-4e17-8b84-eb008afddf69", "endsAt": null, "bidGroupId": null, "amount": null, "bidIndex": null, "address": null, "y": 133, "x": 67, "updatedAt": "2017-12-15T22:03:03.961Z", "id": "67,133", "createdAt": "2017-12-15T22:01:23.340Z"}, {"projectId": "219ac351-e6ce-4e17-8b84-eb008afddf69", "endsAt": null, "bidGroupId": null, "amount": null, "bidIndex": null, "address": null, "y": 133, "x": 68, "updatedAt": "2017-12-15T22:03:03.963Z", "id": "68,133", "createdAt": "2017-12-15T22:01:24.150Z"}, {"projectId": "219ac351-e6ce-4e17-8b84-eb008afddf69", "endsAt": null, "bidGroupId": null, "amount": null, "bidIndex": null, "address": null, "y": 133, "x": 69, "updatedAt": "2017-12-15T22:03:03.966Z", "id": "69,133", "createdAt": "2017-12-15T22:01:24.921Z"}, {"projectId": "219ac351-e6ce-4e17-8b84-eb008afddf69", "endsAt": null, "bidGroupId": null, "amount": null, "bidIndex": null, "address": null, "y": 133, "x": 70, "updatedAt": "2017-12-15T22:03:03.968Z", "id": "70,133", "createdAt": "2017-12-15T22:01:25.725Z"}, {"projectId": "219ac351-e6ce-4e17-8b84-eb008afddf69", "endsAt": null, "bidGroupId": null, "amount": null, "bidIndex": null, "address": null, "y": 133, "x": 71, "updatedAt": "2017-12-15T22:03:03.970Z", "id": "71,133", "createdAt": "2017-12-15T22:01:26.515Z"}, {"projectId": "219ac351-e6ce-4e17-8b84-eb008afddf69", "endsAt": null, "bidGroupId": null, "amount": null, "bidIndex": null, "address": null, "y": 133, "x": 72, "updatedAt": "2017-12-15T22:03:03.972Z", "id": "72,133", "createdAt": "2017-12-15T22:01:27.312Z"}, {"projectId": "219ac351-e6ce-4e17-8b84-eb008afddf69", "endsAt": null, "bidGroupId": null, "amount": null, "bidIndex": null, "address": null, "y": 133, "x": 73, "updatedAt": "2017-12-15T22:03:03.974Z", "id": "73,133", "createdAt": "2017-12-15T22:01:28.106Z"}, {"projectId": "219ac351-e6ce-4e17-8b84-eb008afddf69", "endsAt": null, "bidGroupId": null, "amount": null, "bidIndex": null, "address": null, "y": 133, "x": 74, "updatedAt": "2017-12-15T22:03:03.977Z", "id": "74,133", "createdAt": "2017-12-15T22:01:28.885Z"}, {"projectId": "219ac351-e6ce-4e17-8b84-eb008afddf69", "endsAt": null, "bidGroupId": null, "amount": null, "bidIndex": null, "address": null, "y": 133, "x": 75, "updatedAt": "2017-12-15T22:03:03.979Z", "id": "75,133", "createdAt": "2017-12-15T22:01:29.670Z"}, {"projectId": "219ac351-e6ce-4e17-8b84-eb008afddf69", "endsAt": null, "bidGroupId": null, "amount": null, "bidIndex": null, "address": null, "y": 133, "x": 76, "updatedAt": "2017-12-15T22:03:03.981Z", "id": "76,133", "createdAt": "2017-12-15T22:01:30.500Z"}, {"projectId": "219ac351-e6ce-4e17-8b84-eb008afddf69", "endsAt": null, "bidGroupId": null, "amount": null, "bidIndex": null, "address": null, "y": 133, "x": 77, "updatedAt": "2017-12-15T22:03:03.983Z", "id": "77,133", "createdAt": "2017-12-15T22:01:31.263Z"}, {"projectId": "219ac351-e6ce-4e17-8b84-eb008afddf69", "endsAt": null, "bidGroupId": null, "amount": null, "bidIndex": null, "address": null, "y": 133, "x": 79, "updatedAt": "2017-12-15T22:03:03.988Z", "id": "79,133", "createdAt": "2017-12-15T22:01:32.904Z"}, {"projectId": "219ac351-e6ce-4e17-8b84-eb008afddf69", "endsAt": null, "bidGroupId": null, "amount": null, "bidIndex": null, "address": null, "y": 133, "x": 81, "updatedAt": "2017-12-15T22:03:03.993Z", "id": "81,133", "createdAt": "2017-12-15T22:01:34.575Z"}, {"projectId": "219ac351-e6ce-4e17-8b84-eb008afddf69", "endsAt": null, "bidGroupId": null, "amount": null, "bidIndex": null, "address": null, "y": 133, "x": 83, "updatedAt": "2017-12-15T22:03:03.998Z", "id": "83,133", "createdAt": "2017-12-15T22:01:36.192Z"}, {"projectId": "219ac351-e6ce-4e17-8b84-eb008afddf69", "endsAt": null, "bidGroupId": null, "amount": null, "bidIndex": null, "address": null, "y": 133, "x": 85, "updatedAt": "2017-12-15T22:03:04.010Z", "id": "85,133", "createdAt": "2017-12-15T22:01:37.761Z"}, {"projectId": "219ac351-e6ce-4e17-8b84-eb008afddf69", "endsAt": null, "bidGroupId": null, "amount": null, "bidIndex": null, "address": null, "y": 133, "x": 87, "updatedAt": "2017-12-15T22:03:04.017Z", "id": "87,133", "createdAt": "2017-12-15T22:01:39.337Z"}, {"projectId": "219ac351-e6ce-4e17-8b84-eb008afddf69", "endsAt": null, "bidGroupId": null, "amount": null, "bidIndex": null, "address": null, "y": 133, "x": 89, "updatedAt": "2017-12-15T22:03:04.023Z", "id": "89,133", "createdAt": "2017-12-15T22:01:40.947Z"}, {"projectId": "219ac351-e6ce-4e17-8b84-eb008afddf69", "endsAt": null, "bidGroupId": null, "amount": null, "bidIndex": null, "address": null, "y": 133, "x": 90, "updatedAt": "2017-12-15T22:03:04.027Z", "id": "90,133", "createdAt": "2017-12-15T22:01:41.743Z"}, {"projectId": "219ac351-e6ce-4e17-8b84-eb008afddf69", "endsAt": null, "bidGroupId": null, "amount": null, "bidIndex": null, "address": null, "y": 133, "x": 91, "updatedAt": "2017-12-15T22:03:04.031Z", "id": "91,133", "createdAt": "2017-12-15T22:01:42.593Z"}, {"projectId": "219ac351-e6ce-4e17-8b84-eb008afddf69", "endsAt": null, "bidGroupId": null, "amount": null, "bidIndex": null, "address": null, "y": 133, "x": 92, "updatedAt": "2017-12-15T22:03:04.033Z", "id": "92,133", "createdAt": "2017-12-15T22:01:43.373Z"}, {"projectId": "219ac351-e6ce-4e17-8b84-eb008afddf69", "endsAt": null, "bidGroupId": null, "amount": null, "bidIndex": null, "address": null, "y": 133, "x": 93, "updatedAt": "2017-12-15T22:03:04.036Z", "id": "93,133", "createdAt": "2017-12-15T22:01:44.205Z"}, {"projectId": "219ac351-e6ce-4e17-8b84-eb008afddf69", "endsAt": null, "bidGroupId": null, "amount": null, "bidIndex": null, "address": null, "y": 133, "x": 94, "updatedAt": "2017-12-15T22:03:04.038Z", "id": "94,133", "createdAt": "2017-12-15T22:01:44.991Z"}, {"projectId": "219ac351-e6ce-4e17-8b84-eb008afddf69", "endsAt": null, "bidGroupId": null, "amount": null, "bidIndex": null, "address": null, "y": 133, "x": 95, "updatedAt": "2017-12-15T22:03:04.040Z", "id": "95,133", "createdAt": "2017-12-15T22:01:45.856Z"}, {"projectId": "219ac351-e6ce-4e17-8b84-eb008afddf69", "endsAt": null, "bidGroupId": null, "amount": null, "bidIndex": null, "address": null, "y": 133, "x": 96, "updatedAt": "2017-12-15T22:03:04.043Z", "id": "96,133", "createdAt": "2017-12-15T22:01:46.665Z"}, {"projectId": "219ac351-e6ce-4e17-8b84-eb008afddf69", "endsAt": null, "bidGroupId": null, "amount": null, "bidIndex": null, "address": null, "y": 133, "x": 97, "updatedAt": "2017-12-15T22:03:04.045Z", "id": "97,133", "createdAt": "2017-12-15T22:01:47.489Z"}, {"projectId": "219ac351-e6ce-4e17-8b84-eb008afddf69", "endsAt": null, "bidGroupId": null, "amount": null, "bidIndex": null, "address": null, "y": 133, "x": 98, "updatedAt": "2017-12-15T22:03:04.047Z", "id": "98,133", "createdAt": "2017-12-15T22:01:48.318Z"}, {"projectId": "219ac351-e6ce-4e17-8b84-eb008afddf69", "endsAt": null, "bidGroupId": null, "amount": null, "bidIndex": null, "address": null, "y": 133, "x": 99, "updatedAt": "2017-12-15T22:03:04.050Z", "id": "99,133", "createdAt": "2017-12-15T22:01:49.112Z"}, {"projectId": "219ac351-e6ce-4e17-8b84-eb008afddf69", "endsAt": null, "bidGroupId": null, "amount": null, "bidIndex": null, "address": null, "y": 133, "x": 100, "updatedAt": "2017-12-15T22:03:04.052Z", "id": "100,133", "createdAt": "2017-12-15T22:01:49.919Z"}, {"projectId": "219ac351-e6ce-4e17-8b84-eb008afddf69", "endsAt": null, "bidGroupId": null, "amount": null, "bidIndex": null, "address": null, "y": 133, "x": 101, "updatedAt": "2017-12-15T22:03:04.054Z", "id": "101,133", "createdAt": "2017-12-15T22:01:50.726Z"}, {"projectId": "219ac351-e6ce-4e17-8b84-eb008afddf69", "endsAt": null, "bidGroupId": null, "amount": null, "bidIndex": null, "address": null, "y": 133, "x": 102, "updatedAt": "2017-12-15T22:03:04.057Z", "id": "102,133", "createdAt": "2017-12-15T22:01:51.515Z"}, {"projectId": "219ac351-e6ce-4e17-8b84-eb008afddf69", "endsAt": null, "bidGroupId": null, "amount": null, "bidIndex": null, "address": null, "y": 133, "x": 103, "updatedAt": "2017-12-15T22:03:04.060Z", "id": "103,133", "createdAt": "2017-12-15T22:01:52.327Z"}, {"projectId": "219ac351-e6ce-4e17-8b84-eb008afddf69", "endsAt": null, "bidGroupId": null, "amount": null, "bidIndex": null, "address": null, "y": 133, "x": 104, "updatedAt": "2017-12-15T22:03:04.062Z", "id": "104,133", "createdAt": "2017-12-15T22:01:53.134Z"}, {"projectId": "219ac351-e6ce-4e17-8b84-eb008afddf69", "endsAt": null, "bidGroupId": null, "amount": null, "bidIndex": null, "address": null, "y": 133, "x": 106, "updatedAt": "2017-12-15T22:03:04.068Z", "id": "106,133", "createdAt": "2017-12-15T22:01:54.693Z"}, {"projectId": "219ac351-e6ce-4e17-8b84-eb008afddf69", "endsAt": null, "bidGroupId": null, "amount": null, "bidIndex": null, "address": null, "y": 133, "x": 107, "updatedAt": "2017-12-15T22:03:04.070Z", "id": "107,133", "createdAt": "2017-12-15T22:01:55.450Z"}, {"projectId": "219ac351-e6ce-4e17-8b84-eb008afddf69", "endsAt": null, "bidGroupId": null, "amount": null, "bidIndex": null, "address": null, "y": 133, "x": 108, "updatedAt": "2017-12-15T22:03:04.072Z", "id": "108,133", "createdAt": "2017-12-15T22:01:56.284Z"}, {"projectId": "219ac351-e6ce-4e17-8b84-eb008afddf69", "endsAt": null, "bidGroupId": null, "amount": null, "bidIndex": null, "address": null, "y": 133, "x": 109, "updatedAt": "2017-12-15T22:03:04.074Z", "id": "109,133", "createdAt": "2017-12-15T22:01:57.072Z"}, {"projectId": "219ac351-e6ce-4e17-8b84-eb008afddf69", "endsAt": null, "bidGroupId": null, "amount": null, "bidIndex": null, "address": null, "y": 133, "x": 110, "updatedAt": "2017-12-15T22:03:04.076Z", "id": "110,133", "createdAt": "2017-12-15T22:01:57.924Z"}, {"projectId": "219ac351-e6ce-4e17-8b84-eb008afddf69", "endsAt": null, "bidGroupId": null, "amount": null, "bidIndex": null, "address": null, "y": 133, "x": 111, "updatedAt": "2017-12-15T22:03:04.078Z", "id": "111,133", "createdAt": "2017-12-15T22:01:58.723Z"}, {"projectId": "219ac351-e6ce-4e17-8b84-eb008afddf69", "endsAt": null, "bidGroupId": null, "amount": null, "bidIndex": null, "address": null, "y": 133, "x": 113, "updatedAt": "2017-12-15T22:03:04.084Z", "id": "113,133", "createdAt": "2017-12-15T22:02:00.322Z"}, {"projectId": "219ac351-e6ce-4e17-8b84-eb008afddf69", "endsAt": null, "bidGroupId": null, "amount": null, "bidIndex": null, "address": null, "y": 133, "x": 114, "updatedAt": "2017-12-15T22:03:04.086Z", "id": "114,133", "createdAt": "2017-12-15T22:02:01.132Z"}, {"projectId": "219ac351-e6ce-4e17-8b84-eb008afddf69", "endsAt": null, "bidGroupId": null, "amount": null, "bidIndex": null, "address": null, "y": 133, "x": 115, "updatedAt": "2017-12-15T22:03:04.088Z", "id": "115,133", "createdAt": "2017-12-15T22:02:01.954Z"}, {"projectId": "219ac351-e6ce-4e17-8b84-eb008afddf69", "endsAt": null, "bidGroupId": null, "amount": null, "bidIndex": null, "address": null, "y": 133, "x": 116, "updatedAt": "2017-12-15T22:03:04.090Z", "id": "116,133", "createdAt": "2017-12-15T22:02:02.791Z"}, {"projectId": "219ac351-e6ce-4e17-8b84-eb008afddf69", "endsAt": null, "bidGroupId": null, "amount": null, "bidIndex": null, "address": null, "y": 133, "x": 117, "updatedAt": "2017-12-15T22:03:04.092Z", "id": "117,133", "createdAt": "2017-12-15T22:02:03.558Z"}, {"projectId": "219ac351-e6ce-4e17-8b84-eb008afddf69", "endsAt": null, "bidGroupId": null, "amount": null, "bidIndex": null, "address": null, "y": 133, "x": 118, "updatedAt": "2017-12-15T22:03:04.094Z", "id": "118,133", "createdAt": "2017-12-15T22:02:04.387Z"}, {"projectId": "219ac351-e6ce-4e17-8b84-eb008afddf69", "endsAt": null, "bidGroupId": null, "amount": null, "bidIndex": null, "address": null, "y": 133, "x": 119, "updatedAt": "2017-12-15T22:03:04.097Z", "id": "119,133", "createdAt": "2017-12-15T22:02:05.165Z"}, {"projectId": "219ac351-e6ce-4e17-8b84-eb008afddf69", "endsAt": null, "bidGroupId": null, "amount": null, "bidIndex": null, "address": null, "y": 133, "x": 120, "updatedAt": "2017-12-15T22:03:04.099Z", "id": "120,133", "createdAt": "2017-12-15T22:02:05.981Z"}, {"projectId": "219ac351-e6ce-4e17-8b84-eb008afddf69", "endsAt": null, "bidGroupId": null, "amount": null, "bidIndex": null, "address": null, "y": 133, "x": 122, "updatedAt": "2017-12-15T22:03:04.104Z", "id": "122,133", "createdAt": "2017-12-15T22:02:07.563Z"}, {"projectId": "219ac351-e6ce-4e17-8b84-eb008afddf69", "endsAt": null, "bidGroupId": null, "amount": null, "bidIndex": null, "address": null, "y": 133, "x": 123, "updatedAt": "2017-12-15T22:03:04.106Z", "id": "123,133", "createdAt": "2017-12-15T22:02:08.399Z"}, {"projectId": "219ac351-e6ce-4e17-8b84-eb008afddf69", "endsAt": null, "bidGroupId": null, "amount": null, "bidIndex": null, "address": null, "y": 133, "x": 124, "updatedAt": "2017-12-15T22:03:04.108Z", "id": "124,133", "createdAt": "2017-12-15T22:02:09.178Z"}, {"projectId": "219ac351-e6ce-4e17-8b84-eb008afddf69", "endsAt": null, "bidGroupId": null, "amount": null, "bidIndex": null, "address": null, "y": 133, "x": 125, "updatedAt": "2017-12-15T22:03:04.110Z", "id": "125,133", "createdAt": "2017-12-15T22:02:09.982Z"}, {"projectId": "219ac351-e6ce-4e17-8b84-eb008afddf69", "endsAt": null, "bidGroupId": null, "amount": null, "bidIndex": null, "address": null, "y": 133, "x": 126, "updatedAt": "2017-12-15T22:03:04.112Z", "id": "126,133", "createdAt": "2017-12-15T22:02:10.786Z"}, {"projectId": "219ac351-e6ce-4e17-8b84-eb008afddf69", "endsAt": null, "bidGroupId": null, "amount": null, "bidIndex": null, "address": null, "y": 133, "x": 127, "updatedAt": "2017-12-15T22:03:04.114Z", "id": "127,133", "createdAt": "2017-12-15T22:02:11.577Z"}, {"projectId": "219ac351-e6ce-4e17-8b84-eb008afddf69", "endsAt": null, "bidGroupId": null, "amount": null, "bidIndex": null, "address": null, "y": 133, "x": 128, "updatedAt": "2017-12-15T22:03:04.117Z", "id": "128,133", "createdAt": "2017-12-15T22:02:12.415Z"}, {"projectId": "219ac351-e6ce-4e17-8b84-eb008afddf69", "endsAt": null, "bidGroupId": null, "amount": null, "bidIndex": null, "address": null, "y": 133, "x": 129, "updatedAt": "2017-12-15T22:03:04.119Z", "id": "129,133", "createdAt": "2017-12-15T22:02:13.256Z"}, {"projectId": "219ac351-e6ce-4e17-8b84-eb008afddf69", "endsAt": null, "bidGroupId": null, "amount": null, "bidIndex": null, "address": null, "y": 133, "x": 131, "updatedAt": "2017-12-15T22:03:04.124Z", "id": "131,133", "createdAt": "2017-12-15T22:02:14.864Z"}, {"projectId": "219ac351-e6ce-4e17-8b84-eb008afddf69", "endsAt": null, "bidGroupId": null, "amount": null, "bidIndex": null, "address": null, "y": 133, "x": 132, "updatedAt": "2017-12-15T22:03:04.126Z", "id": "132,133", "createdAt": "2017-12-15T22:02:15.660Z"}, {"projectId": null, "endsAt": "2017-12-24T08:17:14.414Z", "bidGroupId": 32231, "amount": "1954", "bidIndex": 9, "address": "0xb560ff580aabb1c34491c2dd25f96ac127b09413", "y": 133, "x": 24, "updatedAt": "2017-12-23T02:17:14.449Z", "id": "24,133", "createdAt": "2017-12-15T22:00:48.764Z"}, {"projectId": "219ac351-e6ce-4e17-8b84-eb008afddf69", "endsAt": null, "bidGroupId": null, "amount": null, "bidIndex": null, "address": null, "y": 133, "x": 133, "updatedAt": "2017-12-15T22:03:04.129Z", "id": "133,133", "createdAt": "2017-12-15T22:02:16.499Z"}, {"projectId": "219ac351-e6ce-4e17-8b84-eb008afddf69", "endsAt": null, "bidGroupId": null, "amount": null, "bidIndex": null, "address": null, "y": 133, "x": 134, "updatedAt": "2017-12-15T22:03:04.131Z", "id": "134,133", "createdAt": "2017-12-15T22:02:17.295Z"}, {"projectId": "219ac351-e6ce-4e17-8b84-eb008afddf69", "endsAt": null, "bidGroupId": null, "amount": null, "bidIndex": null, "address": null, "y": 133, "x": 135, "updatedAt": "2017-12-15T22:03:04.133Z", "id": "135,133", "createdAt": "2017-12-15T22:02:18.119Z"}, {"projectId": "219ac351-e6ce-4e17-8b84-eb008afddf69", "endsAt": null, "bidGroupId": null, "amount": null, "bidIndex": null, "address": null, "y": 133, "x": 136, "updatedAt": "2017-12-15T22:03:04.136Z", "id": "136,133", "createdAt": "2017-12-15T22:02:18.914Z"}, {"projectId": "219ac351-e6ce-4e17-8b84-eb008afddf69", "endsAt": null, "bidGroupId": null, "amount": null, "bidIndex": null, "address": null, "y": 133, "x": 138, "updatedAt": "2017-12-15T22:03:04.141Z", "id": "138,133", "createdAt": "2017-12-15T22:02:20.530Z"}, {"projectId": "219ac351-e6ce-4e17-8b84-eb008afddf69", "endsAt": null, "bidGroupId": null, "amount": null, "bidIndex": null, "address": null, "y": 133, "x": 139, "updatedAt": "2017-12-15T22:03:04.143Z", "id": "139,133", "createdAt": "2017-12-15T22:02:21.285Z"}, {"projectId": "219ac351-e6ce-4e17-8b84-eb008afddf69", "endsAt": null, "bidGroupId": null, "amount": null, "bidIndex": null, "address": null, "y": 133, "x": 140, "updatedAt": "2017-12-15T22:03:04.146Z", "id": "140,133", "createdAt": "2017-12-15T22:02:22.121Z"}, {"projectId": "219ac351-e6ce-4e17-8b84-eb008afddf69", "endsAt": null, "bidGroupId": null, "amount": null, "bidIndex": null, "address": null, "y": 133, "x": 141, "updatedAt": "2017-12-15T22:03:04.148Z", "id": "141,133", "createdAt": "2017-12-15T22:02:22.904Z"}, {"projectId": "219ac351-e6ce-4e17-8b84-eb008afddf69", "endsAt": null, "bidGroupId": null, "amount": null, "bidIndex": null, "address": null, "y": 133, "x": 142, "updatedAt": "2017-12-15T22:03:04.150Z", "id": "142,133", "createdAt": "2017-12-15T22:02:23.750Z"}, {"projectId": "219ac351-e6ce-4e17-8b84-eb008afddf69", "endsAt": null, "bidGroupId": null, "amount": null, "bidIndex": null, "address": null, "y": 133, "x": 143, "updatedAt": "2017-12-15T22:03:04.152Z", "id": "143,133", "createdAt": "2017-12-15T22:02:24.542Z"}, {"projectId": "219ac351-e6ce-4e17-8b84-eb008afddf69", "endsAt": null, "bidGroupId": null, "amount": null, "bidIndex": null, "address": null, "y": 133, "x": 144, "updatedAt": "2017-12-15T22:03:04.154Z", "id": "144,133", "createdAt": "2017-12-15T22:02:25.331Z"}, {"projectId": "219ac351-e6ce-4e17-8b84-eb008afddf69", "endsAt": null, "bidGroupId": null, "amount": null, "bidIndex": null, "address": null, "y": 133, "x": 145, "updatedAt": "2017-12-15T22:03:04.156Z", "id": "145,133", "createdAt": "2017-12-15T22:02:26.136Z"}, {"projectId": "219ac351-e6ce-4e17-8b84-eb008afddf69", "endsAt": null, "bidGroupId": null, "amount": null, "bidIndex": null, "address": null, "y": 133, "x": 147, "updatedAt": "2017-12-15T22:03:04.161Z", "id": "147,133", "createdAt": "2017-12-15T22:02:27.763Z"}, {"projectId": "219ac351-e6ce-4e17-8b84-eb008afddf69", "endsAt": null, "bidGroupId": null, "amount": null, "bidIndex": null, "address": null, "y": 133, "x": 148, "updatedAt": "2017-12-15T22:03:04.163Z", "id": "148,133", "createdAt": "2017-12-15T22:02:28.568Z"}, {"projectId": "219ac351-e6ce-4e17-8b84-eb008afddf69", "endsAt": null, "bidGroupId": null, "amount": null, "bidIndex": null, "address": null, "y": 133, "x": 149, "updatedAt": "2017-12-15T22:03:04.166Z", "id": "149,133", "createdAt": "2017-12-15T22:02:29.363Z"}, {"projectId": "219ac351-e6ce-4e17-8b84-eb008afddf69", "endsAt": null, "bidGroupId": null, "amount": null, "bidIndex": null, "address": null, "y": 133, "x": 150, "updatedAt": "2017-12-15T22:03:04.168Z", "id": "150,133", "createdAt": "2017-12-15T22:02:30.195Z"}, {"projectId": "81bbd64a-b757-452c-b715-f37a726a0299", "endsAt": null, "bidGroupId": null, "amount": null, "bidIndex": null, "address": null, "y": 133, "x": 52, "updatedAt": "2017-12-15T22:03:28.921Z", "id": "52,133", "createdAt": "2017-12-15T22:01:11.212Z"}, {"projectId": "81bbd64a-b757-452c-b715-f37a726a0299", "endsAt": null, "bidGroupId": null, "amount": null, "bidIndex": null, "address": null, "y": 133, "x": 53, "updatedAt": "2017-12-15T22:03:28.924Z", "id": "53,133", "createdAt": "2017-12-15T22:01:12.095Z"}, {"projectId": "81bbd64a-b757-452c-b715-f37a726a0299", "endsAt": null, "bidGroupId": null, "amount": null, "bidIndex": null, "address": null, "y": 133, "x": 54, "updatedAt": "2017-12-15T22:03:28.926Z", "id": "54,133", "createdAt": "2017-12-15T22:01:12.861Z"}, {"projectId": "81bbd64a-b757-452c-b715-f37a726a0299", "endsAt": null, "bidGroupId": null, "amount": null, "bidIndex": null, "address": null, "y": 133, "x": 55, "updatedAt": "2017-12-15T22:03:28.929Z", "id": "55,133", "createdAt": "2017-12-15T22:01:13.652Z"}, {"projectId": "81bbd64a-b757-452c-b715-f37a726a0299", "endsAt": null, "bidGroupId": null, "amount": null, "bidIndex": null, "address": null, "y": 133, "x": 56, "updatedAt": "2017-12-15T22:03:28.931Z", "id": "56,133", "createdAt": "2017-12-15T22:01:14.451Z"}, {"projectId": "81bbd64a-b757-452c-b715-f37a726a0299", "endsAt": null, "bidGroupId": null, "amount": null, "bidIndex": null, "address": null, "y": 133, "x": 57, "updatedAt": "2017-12-15T22:03:28.934Z", "id": "57,133", "createdAt": "2017-12-15T22:01:15.244Z"}, {"projectId": "81bbd64a-b757-452c-b715-f37a726a0299", "endsAt": null, "bidGroupId": null, "amount": null, "bidIndex": null, "address": null, "y": 133, "x": 58, "updatedAt": "2017-12-15T22:03:28.937Z", "id": "58,133", "createdAt": "2017-12-15T22:01:16.062Z"}, {"projectId": "81bbd64a-b757-452c-b715-f37a726a0299", "endsAt": null, "bidGroupId": null, "amount": null, "bidIndex": null, "address": null, "y": 133, "x": 59, "updatedAt": "2017-12-15T22:03:28.940Z", "id": "59,133", "createdAt": "2017-12-15T22:01:16.854Z"}, {"projectId": "d9bfa18a-c856-457d-8d85-e2dc3b7648a1", "endsAt": null, "bidGroupId": null, "amount": null, "bidIndex": null, "address": null, "y": 133, "x": -150, "updatedAt": "2017-12-15T22:03:41.305Z", "id": "-150,133", "createdAt": "2017-12-15T21:58:27.561Z"}, {"projectId": "d9bfa18a-c856-457d-8d85-e2dc3b7648a1", "endsAt": null, "bidGroupId": null, "amount": null, "bidIndex": null, "address": null, "y": 133, "x": -149, "updatedAt": "2017-12-15T22:03:41.308Z", "id": "-149,133", "createdAt": "2017-12-15T21:58:28.388Z"}, {"projectId": "d9bfa18a-c856-457d-8d85-e2dc3b7648a1", "endsAt": null, "bidGroupId": null, "amount": null, "bidIndex": null, "address": null, "y": 133, "x": -148, "updatedAt": "2017-12-15T22:03:41.314Z", "id": "-148,133", "createdAt": "2017-12-15T21:58:29.175Z"}, {"projectId": "d9bfa18a-c856-457d-8d85-e2dc3b7648a1", "endsAt": null, "bidGroupId": null, "amount": null, "bidIndex": null, "address": null, "y": 133, "x": -147, "updatedAt": "2017-12-15T22:03:41.317Z", "id": "-147,133", "createdAt": "2017-12-15T21:58:29.970Z"}, {"projectId": "d9bfa18a-c856-457d-8d85-e2dc3b7648a1", "endsAt": null, "bidGroupId": null, "amount": null, "bidIndex": null, "address": null, "y": 133, "x": -146, "updatedAt": "2017-12-15T22:03:41.320Z", "id": "-146,133", "createdAt": "2017-12-15T21:58:30.801Z"}, {"projectId": "d9bfa18a-c856-457d-8d85-e2dc3b7648a1", "endsAt": null, "bidGroupId": null, "amount": null, "bidIndex": null, "address": null, "y": 133, "x": -145, "updatedAt": "2017-12-15T22:03:41.323Z", "id": "-145,133", "createdAt": "2017-12-15T21:58:31.572Z"}, {"projectId": "d9bfa18a-c856-457d-8d85-e2dc3b7648a1", "endsAt": null, "bidGroupId": null, "amount": null, "bidIndex": null, "address": null, "y": 133, "x": -144, "updatedAt": "2017-12-15T22:03:41.326Z", "id": "-144,133", "createdAt": "2017-12-15T21:58:32.409Z"}, {"projectId": "d9bfa18a-c856-457d-8d85-e2dc3b7648a1", "endsAt": null, "bidGroupId": null, "amount": null, "bidIndex": null, "address": null, "y": 133, "x": -143, "updatedAt": "2017-12-15T22:03:41.329Z", "id": "-143,133", "createdAt": "2017-12-15T21:58:33.194Z"}, {"projectId": "d9bfa18a-c856-457d-8d85-e2dc3b7648a1", "endsAt": null, "bidGroupId": null, "amount": null, "bidIndex": null, "address": null, "y": 133, "x": -142, "updatedAt": "2017-12-15T22:03:41.331Z", "id": "-142,133", "createdAt": "2017-12-15T21:58:34.088Z"}, {"projectId": "d9bfa18a-c856-457d-8d85-e2dc3b7648a1", "endsAt": null, "bidGroupId": null, "amount": null, "bidIndex": null, "address": null, "y": 133, "x": -141, "updatedAt": "2017-12-15T22:03:41.334Z", "id": "-141,133", "createdAt": "2017-12-15T21:58:34.892Z"}, {"projectId": "d9bfa18a-c856-457d-8d85-e2dc3b7648a1", "endsAt": null, "bidGroupId": null, "amount": null, "bidIndex": null, "address": null, "y": 133, "x": -140, "updatedAt": "2017-12-15T22:03:41.337Z", "id": "-140,133", "createdAt": "2017-12-15T21:58:35.754Z"}, {"projectId": "d9bfa18a-c856-457d-8d85-e2dc3b7648a1", "endsAt": null, "bidGroupId": null, "amount": null, "bidIndex": null, "address": null, "y": 133, "x": -139, "updatedAt": "2017-12-15T22:03:41.339Z", "id": "-139,133", "createdAt": "2017-12-15T21:58:36.562Z"}, {"projectId": "d9bfa18a-c856-457d-8d85-e2dc3b7648a1", "endsAt": null, "bidGroupId": null, "amount": null, "bidIndex": null, "address": null, "y": 133, "x": -138, "updatedAt": "2017-12-15T22:03:41.342Z", "id": "-138,133", "createdAt": "2017-12-15T21:58:37.367Z"}, {"projectId": "d9bfa18a-c856-457d-8d85-e2dc3b7648a1", "endsAt": null, "bidGroupId": null, "amount": null, "bidIndex": null, "address": null, "y": 133, "x": -137, "updatedAt": "2017-12-15T22:03:41.345Z", "id": "-137,133", "createdAt": "2017-12-15T21:58:38.176Z"}, {"projectId": "d9bfa18a-c856-457d-8d85-e2dc3b7648a1", "endsAt": null, "bidGroupId": null, "amount": null, "bidIndex": null, "address": null, "y": 133, "x": -136, "updatedAt": "2017-12-15T22:03:41.348Z", "id": "-136,133", "createdAt": "2017-12-15T21:58:38.962Z"}, {"projectId": "d9bfa18a-c856-457d-8d85-e2dc3b7648a1", "endsAt": null, "bidGroupId": null, "amount": null, "bidIndex": null, "address": null, "y": 133, "x": -135, "updatedAt": "2017-12-15T22:03:41.351Z", "id": "-135,133", "createdAt": "2017-12-15T21:58:39.767Z"}, {"projectId": "d9bfa18a-c856-457d-8d85-e2dc3b7648a1", "endsAt": null, "bidGroupId": null, "amount": null, "bidIndex": null, "address": null, "y": 133, "x": -134, "updatedAt": "2017-12-15T22:03:41.354Z", "id": "-134,133", "createdAt": "2017-12-15T21:58:40.598Z"}, {"projectId": "d9bfa18a-c856-457d-8d85-e2dc3b7648a1", "endsAt": null, "bidGroupId": null, "amount": null, "bidIndex": null, "address": null, "y": 133, "x": -133, "updatedAt": "2017-12-15T22:03:41.357Z", "id": "-133,133", "createdAt": "2017-12-15T21:58:41.412Z"}, {"projectId": "d9bfa18a-c856-457d-8d85-e2dc3b7648a1", "endsAt": null, "bidGroupId": null, "amount": null, "bidIndex": null, "address": null, "y": 133, "x": -132, "updatedAt": "2017-12-15T22:03:41.360Z", "id": "-132,133", "createdAt": "2017-12-15T21:58:42.245Z"}, {"projectId": "d9bfa18a-c856-457d-8d85-e2dc3b7648a1", "endsAt": null, "bidGroupId": null, "amount": null, "bidIndex": null, "address": null, "y": 133, "x": -131, "updatedAt": "2017-12-15T22:03:41.362Z", "id": "-131,133", "createdAt": "2017-12-15T21:58:43.030Z"}, {"projectId": "d9bfa18a-c856-457d-8d85-e2dc3b7648a1", "endsAt": null, "bidGroupId": null, "amount": null, "bidIndex": null, "address": null, "y": 133, "x": -130, "updatedAt": "2017-12-15T22:03:41.365Z", "id": "-130,133", "createdAt": "2017-12-15T21:58:43.864Z"}, {"projectId": "d9bfa18a-c856-457d-8d85-e2dc3b7648a1", "endsAt": null, "bidGroupId": null, "amount": null, "bidIndex": null, "address": null, "y": 133, "x": -129, "updatedAt": "2017-12-15T22:03:41.368Z", "id": "-129,133", "createdAt": "2017-12-15T21:58:44.664Z"}, {"projectId": "d9bfa18a-c856-457d-8d85-e2dc3b7648a1", "endsAt": null, "bidGroupId": null, "amount": null, "bidIndex": null, "address": null, "y": 133, "x": -128, "updatedAt": "2017-12-15T22:03:41.370Z", "id": "-128,133", "createdAt": "2017-12-15T21:58:45.538Z"}, {"projectId": "d9bfa18a-c856-457d-8d85-e2dc3b7648a1", "endsAt": null, "bidGroupId": null, "amount": null, "bidIndex": null, "address": null, "y": 133, "x": -127, "updatedAt": "2017-12-15T22:03:41.373Z", "id": "-127,133", "createdAt": "2017-12-15T21:58:46.377Z"}, {"projectId": "d9bfa18a-c856-457d-8d85-e2dc3b7648a1", "endsAt": null, "bidGroupId": null, "amount": null, "bidIndex": null, "address": null, "y": 133, "x": -126, "updatedAt": "2017-12-15T22:03:41.376Z", "id": "-126,133", "createdAt": "2017-12-15T21:58:47.138Z"}, {"projectId": "d9bfa18a-c856-457d-8d85-e2dc3b7648a1", "endsAt": null, "bidGroupId": null, "amount": null, "bidIndex": null, "address": null, "y": 133, "x": -125, "updatedAt": "2017-12-15T22:03:41.379Z", "id": "-125,133", "createdAt": "2017-12-15T21:58:47.935Z"}, {"projectId": "d9bfa18a-c856-457d-8d85-e2dc3b7648a1", "endsAt": null, "bidGroupId": null, "amount": null, "bidIndex": null, "address": null, "y": 133, "x": -124, "updatedAt": "2017-12-15T22:03:41.384Z", "id": "-124,133", "createdAt": "2017-12-15T21:58:48.752Z"}, {"projectId": "d9bfa18a-c856-457d-8d85-e2dc3b7648a1", "endsAt": null, "bidGroupId": null, "amount": null, "bidIndex": null, "address": null, "y": 133, "x": -123, "updatedAt": "2017-12-15T22:03:41.387Z", "id": "-123,133", "createdAt": "2017-12-15T21:58:49.513Z"}, {"projectId": "d9bfa18a-c856-457d-8d85-e2dc3b7648a1", "endsAt": null, "bidGroupId": null, "amount": null, "bidIndex": null, "address": null, "y": 133, "x": -122, "updatedAt": "2017-12-15T22:03:41.390Z", "id": "-122,133", "createdAt": "2017-12-15T21:58:50.337Z"}, {"projectId": "d9bfa18a-c856-457d-8d85-e2dc3b7648a1", "endsAt": null, "bidGroupId": null, "amount": null, "bidIndex": null, "address": null, "y": 133, "x": -121, "updatedAt": "2017-12-15T22:03:41.393Z", "id": "-121,133", "createdAt": "2017-12-15T21:58:51.136Z"}, {"projectId": "d9bfa18a-c856-457d-8d85-e2dc3b7648a1", "endsAt": null, "bidGroupId": null, "amount": null, "bidIndex": null, "address": null, "y": 133, "x": -120, "updatedAt": "2017-12-15T22:03:41.396Z", "id": "-120,133", "createdAt": "2017-12-15T21:58:51.958Z"}, {"projectId": "d9bfa18a-c856-457d-8d85-e2dc3b7648a1", "endsAt": null, "bidGroupId": null, "amount": null, "bidIndex": null, "address": null, "y": 133, "x": -119, "updatedAt": "2017-12-15T22:03:41.399Z", "id": "-119,133", "createdAt": "2017-12-15T21:58:52.775Z"}, {"projectId": "d9bfa18a-c856-457d-8d85-e2dc3b7648a1", "endsAt": null, "bidGroupId": null, "amount": null, "bidIndex": null, "address": null, "y": 133, "x": -118, "updatedAt": "2017-12-15T22:03:41.402Z", "id": "-118,133", "createdAt": "2017-12-15T21:58:53.544Z"}, {"projectId": "d9bfa18a-c856-457d-8d85-e2dc3b7648a1", "endsAt": null, "bidGroupId": null, "amount": null, "bidIndex": null, "address": null, "y": 133, "x": -117, "updatedAt": "2017-12-15T22:03:41.405Z", "id": "-117,133", "createdAt": "2017-12-15T21:58:54.373Z"}, {"projectId": "d9bfa18a-c856-457d-8d85-e2dc3b7648a1", "endsAt": null, "bidGroupId": null, "amount": null, "bidIndex": null, "address": null, "y": 133, "x": -116, "updatedAt": "2017-12-15T22:03:41.408Z", "id": "-116,133", "createdAt": "2017-12-15T21:58:55.179Z"}, {"projectId": "d9bfa18a-c856-457d-8d85-e2dc3b7648a1", "endsAt": null, "bidGroupId": null, "amount": null, "bidIndex": null, "address": null, "y": 133, "x": -115, "updatedAt": "2017-12-15T22:03:41.410Z", "id": "-115,133", "createdAt": "2017-12-15T21:58:56.002Z"}, {"projectId": "d9bfa18a-c856-457d-8d85-e2dc3b7648a1", "endsAt": null, "bidGroupId": null, "amount": null, "bidIndex": null, "address": null, "y": 133, "x": -114, "updatedAt": "2017-12-15T22:03:41.413Z", "id": "-114,133", "createdAt": "2017-12-15T21:58:56.855Z"}, {"projectId": "d9bfa18a-c856-457d-8d85-e2dc3b7648a1", "endsAt": null, "bidGroupId": null, "amount": null, "bidIndex": null, "address": null, "y": 133, "x": -113, "updatedAt": "2017-12-15T22:03:41.416Z", "id": "-113,133", "createdAt": "2017-12-15T21:58:57.644Z"}, {"projectId": "d9bfa18a-c856-457d-8d85-e2dc3b7648a1", "endsAt": null, "bidGroupId": null, "amount": null, "bidIndex": null, "address": null, "y": 133, "x": -112, "updatedAt": "2017-12-15T22:03:41.418Z", "id": "-112,133", "createdAt": "2017-12-15T21:58:58.465Z"}, {"projectId": "d9bfa18a-c856-457d-8d85-e2dc3b7648a1", "endsAt": null, "bidGroupId": null, "amount": null, "bidIndex": null, "address": null, "y": 133, "x": -111, "updatedAt": "2017-12-15T22:03:41.421Z", "id": "-111,133", "createdAt": "2017-12-15T21:58:59.262Z"}, {"projectId": "d9bfa18a-c856-457d-8d85-e2dc3b7648a1", "endsAt": null, "bidGroupId": null, "amount": null, "bidIndex": null, "address": null, "y": 133, "x": -110, "updatedAt": "2017-12-15T22:03:41.423Z", "id": "-110,133", "createdAt": "2017-12-15T21:59:00.134Z"}, {"projectId": "d9bfa18a-c856-457d-8d85-e2dc3b7648a1", "endsAt": null, "bidGroupId": null, "amount": null, "bidIndex": null, "address": null, "y": 133, "x": -109, "updatedAt": "2017-12-15T22:03:41.428Z", "id": "-109,133", "createdAt": "2017-12-15T21:59:00.930Z"}, {"projectId": "d9bfa18a-c856-457d-8d85-e2dc3b7648a1", "endsAt": null, "bidGroupId": null, "amount": null, "bidIndex": null, "address": null, "y": 133, "x": -108, "updatedAt": "2017-12-15T22:03:41.430Z", "id": "-108,133", "createdAt": "2017-12-15T21:59:01.758Z"}, {"projectId": "d9bfa18a-c856-457d-8d85-e2dc3b7648a1", "endsAt": null, "bidGroupId": null, "amount": null, "bidIndex": null, "address": null, "y": 133, "x": -107, "updatedAt": "2017-12-15T22:03:41.433Z", "id": "-107,133", "createdAt": "2017-12-15T21:59:02.543Z"}, {"projectId": "d9bfa18a-c856-457d-8d85-e2dc3b7648a1", "endsAt": null, "bidGroupId": null, "amount": null, "bidIndex": null, "address": null, "y": 133, "x": -106, "updatedAt": "2017-12-15T22:03:41.436Z", "id": "-106,133", "createdAt": "2017-12-15T21:59:03.277Z"}, {"projectId": "d9bfa18a-c856-457d-8d85-e2dc3b7648a1", "endsAt": null, "bidGroupId": null, "amount": null, "bidIndex": null, "address": null, "y": 133, "x": -105, "updatedAt": "2017-12-15T22:03:41.438Z", "id": "-105,133", "createdAt": "2017-12-15T21:59:04.086Z"}, {"projectId": "d9bfa18a-c856-457d-8d85-e2dc3b7648a1", "endsAt": null, "bidGroupId": null, "amount": null, "bidIndex": null, "address": null, "y": 133, "x": -104, "updatedAt": "2017-12-15T22:03:41.441Z", "id": "-104,133", "createdAt": "2017-12-15T21:59:04.889Z"}, {"projectId": "d9bfa18a-c856-457d-8d85-e2dc3b7648a1", "endsAt": null, "bidGroupId": null, "amount": null, "bidIndex": null, "address": null, "y": 133, "x": -103, "updatedAt": "2017-12-15T22:03:41.443Z", "id": "-103,133", "createdAt": "2017-12-15T21:59:05.674Z"}, {"projectId": "d9bfa18a-c856-457d-8d85-e2dc3b7648a1", "endsAt": null, "bidGroupId": null, "amount": null, "bidIndex": null, "address": null, "y": 133, "x": -102, "updatedAt": "2017-12-15T22:03:41.446Z", "id": "-102,133", "createdAt": "2017-12-15T21:59:06.501Z"}, {"projectId": "d9bfa18a-c856-457d-8d85-e2dc3b7648a1", "endsAt": null, "bidGroupId": null, "amount": null, "bidIndex": null, "address": null, "y": 133, "x": -101, "updatedAt": "2017-12-15T22:03:41.449Z", "id": "-101,133", "createdAt": "2017-12-15T21:59:07.349Z"}, {"projectId": "d9bfa18a-c856-457d-8d85-e2dc3b7648a1", "endsAt": null, "bidGroupId": null, "amount": null, "bidIndex": null, "address": null, "y": 133, "x": -100, "updatedAt": "2017-12-15T22:03:41.452Z", "id": "-100,133", "createdAt": "2017-12-15T21:59:08.131Z"}, {"projectId": "d9bfa18a-c856-457d-8d85-e2dc3b7648a1", "endsAt": null, "bidGroupId": null, "amount": null, "bidIndex": null, "address": null, "y": 133, "x": -99, "updatedAt": "2017-12-15T22:03:41.454Z", "id": "-99,133", "createdAt": "2017-12-15T21:59:08.921Z"}, {"projectId": "d9bfa18a-c856-457d-8d85-e2dc3b7648a1", "endsAt": null, "bidGroupId": null, "amount": null, "bidIndex": null, "address": null, "y": 133, "x": -98, "updatedAt": "2017-12-15T22:03:41.457Z", "id": "-98,133", "createdAt": "2017-12-15T21:59:09.736Z"}, {"projectId": "d9bfa18a-c856-457d-8d85-e2dc3b7648a1", "endsAt": null, "bidGroupId": null, "amount": null, "bidIndex": null, "address": null, "y": 133, "x": -97, "updatedAt": "2017-12-15T22:03:41.459Z", "id": "-97,133", "createdAt": "2017-12-15T21:59:10.511Z"}, {"projectId": "d9bfa18a-c856-457d-8d85-e2dc3b7648a1", "endsAt": null, "bidGroupId": null, "amount": null, "bidIndex": null, "address": null, "y": 133, "x": -96, "updatedAt": "2017-12-15T22:03:41.462Z", "id": "-96,133", "createdAt": "2017-12-15T21:59:11.310Z"}, {"projectId": "d9bfa18a-c856-457d-8d85-e2dc3b7648a1", "endsAt": null, "bidGroupId": null, "amount": null, "bidIndex": null, "address": null, "y": 133, "x": -95, "updatedAt": "2017-12-15T22:03:41.465Z", "id": "-95,133", "createdAt": "2017-12-15T21:59:12.190Z"}, {"projectId": "d9bfa18a-c856-457d-8d85-e2dc3b7648a1", "endsAt": null, "bidGroupId": null, "amount": null, "bidIndex": null, "address": null, "y": 133, "x": -94, "updatedAt": "2017-12-15T22:03:41.467Z", "id": "-94,133", "createdAt": "2017-12-15T21:59:12.973Z"}, {"projectId": "d9bfa18a-c856-457d-8d85-e2dc3b7648a1", "endsAt": null, "bidGroupId": null, "amount": null, "bidIndex": null, "address": null, "y": 133, "x": -93, "updatedAt": "2017-12-15T22:03:41.470Z", "id": "-93,133", "createdAt": "2017-12-15T21:59:13.760Z"}, {"projectId": "d9bfa18a-c856-457d-8d85-e2dc3b7648a1", "endsAt": null, "bidGroupId": null, "amount": null, "bidIndex": null, "address": null, "y": 133, "x": -92, "updatedAt": "2017-12-15T22:03:41.473Z", "id": "-92,133", "createdAt": "2017-12-15T21:59:14.553Z"}, {"projectId": "d9bfa18a-c856-457d-8d85-e2dc3b7648a1", "endsAt": null, "bidGroupId": null, "amount": null, "bidIndex": null, "address": null, "y": 133, "x": -91, "updatedAt": "2017-12-15T22:03:41.476Z", "id": "-91,133", "createdAt": "2017-12-15T21:59:15.361Z"}, {"projectId": "d9bfa18a-c856-457d-8d85-e2dc3b7648a1", "endsAt": null, "bidGroupId": null, "amount": null, "bidIndex": null, "address": null, "y": 133, "x": -90, "updatedAt": "2017-12-15T22:03:41.479Z", "id": "-90,133", "createdAt": "2017-12-15T21:59:16.163Z"}, {"projectId": "d9bfa18a-c856-457d-8d85-e2dc3b7648a1", "endsAt": null, "bidGroupId": null, "amount": null, "bidIndex": null, "address": null, "y": 133, "x": -89, "updatedAt": "2017-12-15T22:03:41.482Z", "id": "-89,133", "createdAt": "2017-12-15T21:59:17.022Z"}, {"projectId": "d9bfa18a-c856-457d-8d85-e2dc3b7648a1", "endsAt": null, "bidGroupId": null, "amount": null, "bidIndex": null, "address": null, "y": 133, "x": -88, "updatedAt": "2017-12-15T22:03:41.485Z", "id": "-88,133", "createdAt": "2017-12-15T21:59:17.775Z"}, {"projectId": "d9bfa18a-c856-457d-8d85-e2dc3b7648a1", "endsAt": null, "bidGroupId": null, "amount": null, "bidIndex": null, "address": null, "y": 133, "x": -87, "updatedAt": "2017-12-15T22:03:41.487Z", "id": "-87,133", "createdAt": "2017-12-15T21:59:18.542Z"}, {"projectId": "d9bfa18a-c856-457d-8d85-e2dc3b7648a1", "endsAt": null, "bidGroupId": null, "amount": null, "bidIndex": null, "address": null, "y": 133, "x": -86, "updatedAt": "2017-12-15T22:03:41.490Z", "id": "-86,133", "createdAt": "2017-12-15T21:59:19.310Z"}, {"projectId": "d9bfa18a-c856-457d-8d85-e2dc3b7648a1", "endsAt": null, "bidGroupId": null, "amount": null, "bidIndex": null, "address": null, "y": 133, "x": -85, "updatedAt": "2017-12-15T22:03:41.493Z", "id": "-85,133", "createdAt": "2017-12-15T21:59:20.095Z"}, {"projectId": "d9bfa18a-c856-457d-8d85-e2dc3b7648a1", "endsAt": null, "bidGroupId": null, "amount": null, "bidIndex": null, "address": null, "y": 133, "x": -84, "updatedAt": "2017-12-15T22:03:41.496Z", "id": "-84,133", "createdAt": "2017-12-15T21:59:20.906Z"}, {"projectId": "d9bfa18a-c856-457d-8d85-e2dc3b7648a1", "endsAt": null, "bidGroupId": null, "amount": null, "bidIndex": null, "address": null, "y": 133, "x": -83, "updatedAt": "2017-12-15T22:03:41.499Z", "id": "-83,133", "createdAt": "2017-12-15T21:59:21.733Z"}, {"projectId": "d9bfa18a-c856-457d-8d85-e2dc3b7648a1", "endsAt": null, "bidGroupId": null, "amount": null, "bidIndex": null, "address": null, "y": 133, "x": -82, "updatedAt": "2017-12-15T22:03:41.502Z", "id": "-82,133", "createdAt": "2017-12-15T21:59:22.584Z"}, {"projectId": "d9bfa18a-c856-457d-8d85-e2dc3b7648a1", "endsAt": null, "bidGroupId": null, "amount": null, "bidIndex": null, "address": null, "y": 133, "x": -81, "updatedAt": "2017-12-15T22:03:41.506Z", "id": "-81,133", "createdAt": "2017-12-15T21:59:23.372Z"}, {"projectId": "d9bfa18a-c856-457d-8d85-e2dc3b7648a1", "endsAt": null, "bidGroupId": null, "amount": null, "bidIndex": null, "address": null, "y": 133, "x": -80, "updatedAt": "2017-12-15T22:03:41.509Z", "id": "-80,133", "createdAt": "2017-12-15T21:59:24.197Z"}, {"projectId": "d9bfa18a-c856-457d-8d85-e2dc3b7648a1", "endsAt": null, "bidGroupId": null, "amount": null, "bidIndex": null, "address": null, "y": 133, "x": -79, "updatedAt": "2017-12-15T22:03:41.512Z", "id": "-79,133", "createdAt": "2017-12-15T21:59:25.000Z"}, {"projectId": "d9bfa18a-c856-457d-8d85-e2dc3b7648a1", "endsAt": null, "bidGroupId": null, "amount": null, "bidIndex": null, "address": null, "y": 133, "x": -78, "updatedAt": "2017-12-15T22:03:41.515Z", "id": "-78,133", "createdAt": "2017-12-15T21:59:25.806Z"}, {"projectId": "d9bfa18a-c856-457d-8d85-e2dc3b7648a1", "endsAt": null, "bidGroupId": null, "amount": null, "bidIndex": null, "address": null, "y": 133, "x": -77, "updatedAt": "2017-12-15T22:03:41.518Z", "id": "-77,133", "createdAt": "2017-12-15T21:59:26.619Z"}, {"projectId": "d9bfa18a-c856-457d-8d85-e2dc3b7648a1", "endsAt": null, "bidGroupId": null, "amount": null, "bidIndex": null, "address": null, "y": 133, "x": -76, "updatedAt": "2017-12-15T22:03:41.521Z", "id": "-76,133", "createdAt": "2017-12-15T21:59:27.481Z"}, {"projectId": "d9bfa18a-c856-457d-8d85-e2dc3b7648a1", "endsAt": null, "bidGroupId": null, "amount": null, "bidIndex": null, "address": null, "y": 133, "x": -75, "updatedAt": "2017-12-15T22:03:41.524Z", "id": "-75,133", "createdAt": "2017-12-15T21:59:28.297Z"}, {"projectId": "d9bfa18a-c856-457d-8d85-e2dc3b7648a1", "endsAt": null, "bidGroupId": null, "amount": null, "bidIndex": null, "address": null, "y": 133, "x": -74, "updatedAt": "2017-12-15T22:03:41.527Z", "id": "-74,133", "createdAt": "2017-12-15T21:59:29.095Z"}, {"projectId": "f77140f9-c7b4-4787-89c9-9fa0e219b079", "endsAt": null, "bidGroupId": null, "amount": null, "bidIndex": null, "address": null, "y": 133, "x": -73, "updatedAt": "2017-12-15T22:04:14.731Z", "id": "-73,133", "createdAt": "2017-12-15T21:59:29.921Z"}, {"projectId": "f77140f9-c7b4-4787-89c9-9fa0e219b079", "endsAt": null, "bidGroupId": null, "amount": null, "bidIndex": null, "address": null, "y": 133, "x": -72, "updatedAt": "2017-12-15T22:04:14.733Z", "id": "-72,133", "createdAt": "2017-12-15T21:59:30.739Z"}, {"projectId": "f77140f9-c7b4-4787-89c9-9fa0e219b079", "endsAt": null, "bidGroupId": null, "amount": null, "bidIndex": null, "address": null, "y": 133, "x": -37, "updatedAt": "2017-12-15T22:04:14.735Z", "id": "-37,133", "createdAt": "2017-12-15T21:59:59.251Z"}, {"projectId": "f77140f9-c7b4-4787-89c9-9fa0e219b079", "endsAt": null, "bidGroupId": null, "amount": null, "bidIndex": null, "address": null, "y": 133, "x": -36, "updatedAt": "2017-12-15T22:04:14.738Z", "id": "-36,133", "createdAt": "2017-12-15T22:00:00.182Z"}, {"projectId": "f77140f9-c7b4-4787-89c9-9fa0e219b079", "endsAt": null, "bidGroupId": null, "amount": null, "bidIndex": null, "address": null, "y": 133, "x": 1, "updatedAt": "2017-12-15T22:04:14.741Z", "id": "1,133", "createdAt": "2017-12-15T22:00:30.005Z"}, {"projectId": "f77140f9-c7b4-4787-89c9-9fa0e219b079", "endsAt": null, "bidGroupId": null, "amount": null, "bidIndex": null, "address": null, "y": 133, "x": 2, "updatedAt": "2017-12-15T22:04:14.743Z", "id": "2,133", "createdAt": "2017-12-15T22:00:30.868Z"}, {"projectId": "f77140f9-c7b4-4787-89c9-9fa0e219b079", "endsAt": null, "bidGroupId": null, "amount": null, "bidIndex": null, "address": null, "y": 133, "x": 4, "updatedAt": "2017-12-15T22:04:14.748Z", "id": "4,133", "createdAt": "2017-12-15T22:00:32.490Z"}, {"projectId": "f77140f9-c7b4-4787-89c9-9fa0e219b079", "endsAt": null, "bidGroupId": null, "amount": null, "bidIndex": null, "address": null, "y": 133, "x": 6, "updatedAt": "2017-12-15T22:04:14.753Z", "id": "6,133", "createdAt": "2017-12-15T22:00:34.155Z"}, {"projectId": "f77140f9-c7b4-4787-89c9-9fa0e219b079", "endsAt": null, "bidGroupId": null, "amount": null, "bidIndex": null, "address": null, "y": 133, "x": 8, "updatedAt": "2017-12-15T22:04:14.758Z", "id": "8,133", "createdAt": "2017-12-15T22:00:35.757Z"}, {"projectId": "f77140f9-c7b4-4787-89c9-9fa0e219b079", "endsAt": null, "bidGroupId": null, "amount": null, "bidIndex": null, "address": null, "y": 133, "x": 10, "updatedAt": "2017-12-15T22:04:14.762Z", "id": "10,133", "createdAt": "2017-12-15T22:00:37.325Z"}, {"projectId": "f77140f9-c7b4-4787-89c9-9fa0e219b079", "endsAt": null, "bidGroupId": null, "amount": null, "bidIndex": null, "address": null, "y": 133, "x": 12, "updatedAt": "2017-12-15T22:04:14.768Z", "id": "12,133", "createdAt": "2017-12-15T22:00:38.940Z"}, {"projectId": "f77140f9-c7b4-4787-89c9-9fa0e219b079", "endsAt": null, "bidGroupId": null, "amount": null, "bidIndex": null, "address": null, "y": 133, "x": 14, "updatedAt": "2017-12-15T22:04:14.773Z", "id": "14,133", "createdAt": "2017-12-15T22:00:40.555Z"}, {"projectId": "f77140f9-c7b4-4787-89c9-9fa0e219b079", "endsAt": null, "bidGroupId": null, "amount": null, "bidIndex": null, "address": null, "y": 133, "x": 16, "updatedAt": "2017-12-15T22:04:14.778Z", "id": "16,133", "createdAt": "2017-12-15T22:00:42.229Z"}, {"projectId": "f77140f9-c7b4-4787-89c9-9fa0e219b079", "endsAt": null, "bidGroupId": null, "amount": null, "bidIndex": null, "address": null, "y": 133, "x": 17, "updatedAt": "2017-12-15T22:04:14.781Z", "id": "17,133", "createdAt": "2017-12-15T22:00:43.022Z"}, {"projectId": "f77140f9-c7b4-4787-89c9-9fa0e219b079", "endsAt": null, "bidGroupId": null, "amount": null, "bidIndex": null, "address": null, "y": 133, "x": 18, "updatedAt": "2017-12-15T22:04:14.784Z", "id": "18,133", "createdAt": "2017-12-15T22:00:43.831Z"}, {"projectId": "f77140f9-c7b4-4787-89c9-9fa0e219b079", "endsAt": null, "bidGroupId": null, "amount": null, "bidIndex": null, "address": null, "y": 133, "x": 19, "updatedAt": "2017-12-15T22:04:14.787Z", "id": "19,133", "createdAt": "2017-12-15T22:00:44.627Z"}, {"projectId": "f77140f9-c7b4-4787-89c9-9fa0e219b079", "endsAt": null, "bidGroupId": null, "amount": null, "bidIndex": null, "address": null, "y": 133, "x": 34, "updatedAt": "2017-12-15T22:04:14.790Z", "id": "34,133", "createdAt": "2017-12-15T22:00:56.812Z"}, {"projectId": "f77140f9-c7b4-4787-89c9-9fa0e219b079", "endsAt": null, "bidGroupId": null, "amount": null, "bidIndex": null, "address": null, "y": 133, "x": 35, "updatedAt": "2017-12-15T22:04:14.793Z", "id": "35,133", "createdAt": "2017-12-15T22:00:57.598Z"}, {"projectId": "f77140f9-c7b4-4787-89c9-9fa0e219b079", "endsAt": null, "bidGroupId": null, "amount": null, "bidIndex": null, "address": null, "y": 133, "x": 60, "updatedAt": "2017-12-15T22:04:14.796Z", "id": "60,133", "createdAt": "2017-12-15T22:01:17.662Z"}, {"projectId": "f77140f9-c7b4-4787-89c9-9fa0e219b079", "endsAt": null, "bidGroupId": null, "amount": null, "bidIndex": null, "address": null, "y": 133, "x": 61, "updatedAt": "2017-12-15T22:04:14.799Z", "id": "61,133", "createdAt": "2017-12-15T22:01:18.468Z"}, {"projectId": null, "endsAt": "2017-12-22T22:00:00.000Z", "bidGroupId": 18059, "amount": "1000", "bidIndex": 10, "address": "0x1463b7162103247c5d464f104f7c9da61dea1bfc", "y": 133, "x": -55, "updatedAt": "2017-12-20T19:25:41.944Z", "id": "-55,133", "createdAt": "2017-12-15T21:59:44.582Z"}, {"projectId": null, "endsAt": "2017-12-22T22:00:00.000Z", "bidGroupId": 18059, "amount": "1000", "bidIndex": 11, "address": "0x1463b7162103247c5d464f104f7c9da61dea1bfc", "y": 133, "x": -54, "updatedAt": "2017-12-20T19:25:41.945Z", "id": "-54,133", "createdAt": "2017-12-15T21:59:45.435Z"}, {"projectId": null, "endsAt": "2017-12-22T22:00:00.000Z", "bidGroupId": 18059, "amount": "1000", "bidIndex": 12, "address": "0x1463b7162103247c5d464f104f7c9da61dea1bfc", "y": 133, "x": -53, "updatedAt": "2017-12-20T19:25:41.945Z", "id": "-53,133", "createdAt": "2017-12-15T21:59:46.260Z"}, {"projectId": null, "endsAt": "2017-12-22T22:00:00.000Z", "bidGroupId": 18059, "amount": "1000", "bidIndex": 13, "address": "0x1463b7162103247c5d464f104f7c9da61dea1bfc", "y": 133, "x": -52, "updatedAt": "2017-12-20T19:25:41.946Z", "id": "-52,133", "createdAt": "2017-12-15T21:59:47.118Z"}, {"projectId": null, "endsAt": "2017-12-22T22:00:00.000Z", "bidGroupId": 18059, "amount": "1000", "bidIndex": 14, "address": "0x1463b7162103247c5d464f104f7c9da61dea1bfc", "y": 133, "x": -51, "updatedAt": "2017-12-20T19:25:41.946Z", "id": "-51,133", "createdAt": "2017-12-15T21:59:47.935Z"}, {"projectId": null, "endsAt": "2017-12-22T22:00:00.000Z", "bidGroupId": 18059, "amount": "1000", "bidIndex": 22, "address": "0x1463b7162103247c5d464f104f7c9da61dea1bfc", "y": 133, "x": -50, "updatedAt": "2017-12-20T19:25:41.951Z", "id": "-50,133", "createdAt": "2017-12-15T21:59:48.786Z"}, {"projectId": null, "endsAt": "2017-12-26T05:38:01.164Z", "bidGroupId": 41773, "amount": "3000", "bidIndex": 3, "address": "0x2bea3dfaaac3e05e7a13b9e5bc1fe1f217b29eb6", "y": 133, "x": -44, "updatedAt": "2017-12-24T23:38:01.182Z", "id": "-44,133", "createdAt": "2017-12-15T21:59:53.556Z"}, {"projectId": null, "endsAt": "2017-12-30T08:26:28.016Z", "bidGroupId": 47350, "amount": "5967", "bidIndex": 0, "address": "0x0a98019447660c875cce6d82d90d69933c6455b9", "y": 133, "x": -57, "updatedAt": "2017-12-29T02:26:28.026Z", "id": "-57,133", "createdAt": "2017-12-15T21:59:42.957Z"}, {"projectId": null, "endsAt": "2017-12-26T09:57:16.058Z", "bidGroupId": 42464, "amount": "2443", "bidIndex": 0, "address": "0x04a2f39dc09f1953d9cb5e127df8e4d0ccd3f23d", "y": 133, "x": -48, "updatedAt": "2017-12-25T03:57:16.065Z", "id": "-48,133", "createdAt": "2017-12-15T21:59:50.364Z"}, {"projectId": null, "endsAt": "2017-12-27T13:45:22.605Z", "bidGroupId": 45170, "amount": "3054", "bidIndex": 7, "address": "0xccd5089557ae6a2ba063e8720e725a6bf743b3e8", "y": 133, "x": -41, "updatedAt": "2017-12-26T07:45:22.640Z", "id": "-41,133", "createdAt": "2017-12-15T21:59:55.977Z"}, {"projectId": null, "endsAt": "2017-12-27T13:45:22.605Z", "bidGroupId": 45170, "amount": "3054", "bidIndex": 11, "address": "0xccd5089557ae6a2ba063e8720e725a6bf743b3e8", "y": 133, "x": -40, "updatedAt": "2017-12-26T07:45:22.643Z", "id": "-40,133", "createdAt": "2017-12-15T21:59:56.775Z"}, {"projectId": null, "endsAt": "2017-12-24T00:08:54.407Z", "bidGroupId": 27897, "amount": "1250", "bidIndex": 73, "address": "0xf25e635a9f35c97df49c52637eddcdca64259ef8", "y": 133, "x": -49, "updatedAt": "2017-12-22T18:08:54.642Z", "id": "-49,133", "createdAt": "2017-12-15T21:59:49.539Z"}, {"projectId": null, "endsAt": "2017-12-28T16:52:15.530Z", "bidGroupId": 46485, "amount": "4773", "bidIndex": 1, "address": "0x2bea3dfaaac3e05e7a13b9e5bc1fe1f217b29eb6", "y": 133, "x": -39, "updatedAt": "2017-12-27T10:52:15.541Z", "id": "-39,133", "createdAt": "2017-12-15T21:59:57.601Z"}, {"projectId": null, "endsAt": "2017-12-26T05:28:24.749Z", "bidGroupId": 41740, "amount": "2443", "bidIndex": 0, "address": "0x2bea3dfaaac3e05e7a13b9e5bc1fe1f217b29eb6", "y": 133, "x": -46, "updatedAt": "2017-12-24T23:28:24.756Z", "id": "-46,133", "createdAt": "2017-12-15T21:59:51.928Z"}, {"projectId": null, "endsAt": "2017-12-31T06:02:46.812Z", "bidGroupId": 47534, "amount": "9324", "bidIndex": 0, "address": "0x2bea3dfaaac3e05e7a13b9e5bc1fe1f217b29eb6", "y": 133, "x": -47, "updatedAt": "2017-12-30T00:02:46.819Z", "id": "-47,133", "createdAt": "2017-12-15T21:59:51.125Z"}, {"projectId": null, "endsAt": "2017-12-25T23:23:55.494Z", "bidGroupId": 40988, "amount": "9324", "bidIndex": 0, "address": "0x8fed92510f24b3bf86638a6165dea6f8f0aeff89", "y": 133, "x": 21, "updatedAt": "2017-12-24T17:23:55.510Z", "id": "21,133", "createdAt": "2017-12-15T22:00:46.324Z"}, {"projectId": null, "endsAt": "2017-12-23T05:20:04.228Z", "bidGroupId": 23335, "amount": "3818", "bidIndex": 0, "address": "0xb522bd8a501dfa970c40b57eb76c76256d55758d", "y": 133, "x": -71, "updatedAt": "2017-12-21T23:20:04.256Z", "id": "-71,133", "createdAt": "2017-12-15T21:59:31.535Z"}, {"projectId": null, "endsAt": "2017-12-24T06:35:15.996Z", "bidGroupId": 31648, "amount": "2443", "bidIndex": 4, "address": "0xb522bd8a501dfa970c40b57eb76c76256d55758d", "y": 133, "x": -70, "updatedAt": "2017-12-23T00:35:16.039Z", "id": "-70,133", "createdAt": "2017-12-15T21:59:32.364Z"}, {"projectId": null, "endsAt": "2017-12-24T06:35:15.996Z", "bidGroupId": 31648, "amount": "2443", "bidIndex": 5, "address": "0xb522bd8a501dfa970c40b57eb76c76256d55758d", "y": 133, "x": -69, "updatedAt": "2017-12-23T00:35:16.040Z", "id": "-69,133", "createdAt": "2017-12-15T21:59:33.138Z"}, {"projectId": null, "endsAt": "2017-12-24T06:35:15.996Z", "bidGroupId": 31648, "amount": "1563", "bidIndex": 10, "address": "0xb522bd8a501dfa970c40b57eb76c76256d55758d", "y": 133, "x": -68, "updatedAt": "2017-12-23T00:35:16.044Z", "id": "-68,133", "createdAt": "2017-12-15T21:59:33.983Z"}, {"projectId": null, "endsAt": "2017-12-28T15:14:27.498Z", "bidGroupId": 46425, "amount": "10000", "bidIndex": 0, "address": "0x2bea3dfaaac3e05e7a13b9e5bc1fe1f217b29eb6", "y": 133, "x": -38, "updatedAt": "2017-12-27T09:14:27.504Z", "id": "-38,133", "createdAt": "2017-12-15T21:59:58.410Z"}, {"projectId": null, "endsAt": "2017-12-22T22:00:00.000Z", "bidGroupId": 2346, "amount": "1000", "bidIndex": 8, "address": "0xb522bd8a501dfa970c40b57eb76c76256d55758d", "y": 133, "x": -66, "updatedAt": "2017-12-16T01:36:10.875Z", "id": "-66,133", "createdAt": "2017-12-15T21:59:35.551Z"}, {"projectId": null, "endsAt": "2017-12-22T22:00:00.000Z", "bidGroupId": 2346, "amount": "1000", "bidIndex": 9, "address": "0xb522bd8a501dfa970c40b57eb76c76256d55758d", "y": 133, "x": -67, "updatedAt": "2017-12-16T01:36:10.878Z", "id": "-67,133", "createdAt": "2017-12-15T21:59:34.786Z"}, {"projectId": null, "endsAt": "2017-12-26T15:51:16.160Z", "bidGroupId": 43138, "amount": "22765", "bidIndex": 0, "address": "0x8fed92510f24b3bf86638a6165dea6f8f0aeff89", "y": 133, "x": 20, "updatedAt": "2017-12-25T09:51:16.167Z", "id": "20,133", "createdAt": "2017-12-15T22:00:45.490Z"}, {"projectId": null, "endsAt": "2017-12-25T04:48:35.667Z", "bidGroupId": 37221, "amount": "1613", "bidIndex": 25, "address": "0x38001a6ab8d70bab89333d9e945c847cbeb8c477", "y": 133, "x": 32, "updatedAt": "2017-12-23T22:48:35.782Z", "id": "32,133", "createdAt": "2017-12-15T22:00:55.181Z"}, {"projectId": null, "endsAt": "2017-12-26T20:32:59.235Z", "bidGroupId": 43817, "amount": "5967", "bidIndex": 2, "address": "0x8fed92510f24b3bf86638a6165dea6f8f0aeff89", "y": 133, "x": 22, "updatedAt": "2017-12-25T14:32:59.251Z", "id": "22,133", "createdAt": "2017-12-15T22:00:47.148Z"}, {"projectId": null, "endsAt": "2017-12-24T23:23:59.720Z", "bidGroupId": 36054, "amount": "1563", "bidIndex": 4, "address": "0xb560ff580aabb1c34491c2dd25f96ac127b09413", "y": 133, "x": 26, "updatedAt": "2017-12-23T17:23:59.744Z", "id": "26,133", "createdAt": "2017-12-15T22:00:50.371Z"}, {"projectId": null, "endsAt": "2017-12-29T02:13:40.965Z", "bidGroupId": 46776, "amount": "4773", "bidIndex": 1, "address": "0x38001a6ab8d70bab89333d9e945c847cbeb8c477", "y": 133, "x": 31, "updatedAt": "2017-12-27T20:13:40.996Z", "id": "31,133", "createdAt": "2017-12-15T22:00:54.406Z"}, {"projectId": null, "endsAt": "2017-12-27T03:24:34.197Z", "bidGroupId": 44513, "amount": "4928", "bidIndex": 1, "address": "0x38001a6ab8d70bab89333d9e945c847cbeb8c477", "y": 133, "x": 33, "updatedAt": "2017-12-25T21:24:34.208Z", "id": "33,133", "createdAt": "2017-12-15T22:00:56.010Z"}, {"projectId": null, "endsAt": "2017-12-22T22:00:00.000Z", "bidGroupId": 7499, "amount": "1250", "bidIndex": 2, "address": "0x521b0fef9cdcf250abaf8e7bc798cbe13fa98692", "y": 133, "x": 51, "updatedAt": "2017-12-16T11:36:26.655Z", "id": "51,133", "createdAt": "2017-12-15T22:01:10.426Z"}, {"projectId": null, "endsAt": "2017-12-24T23:23:59.720Z", "bidGroupId": 36054, "amount": "1563", "bidIndex": 3, "address": "0xb560ff580aabb1c34491c2dd25f96ac127b09413", "y": 133, "x": 25, "updatedAt": "2017-12-23T17:23:59.743Z", "id": "25,133", "createdAt": "2017-12-15T22:00:49.555Z"}, {"projectId": null, "endsAt": "2017-12-24T23:23:59.720Z", "bidGroupId": 36054, "amount": "1563", "bidIndex": 5, "address": "0xb560ff580aabb1c34491c2dd25f96ac127b09413", "y": 133, "x": 27, "updatedAt": "2017-12-23T17:23:59.744Z", "id": "27,133", "createdAt": "2017-12-15T22:00:51.209Z"}, {"projectId": null, "endsAt": "2017-12-24T08:17:14.414Z", "bidGroupId": 32231, "amount": "1954", "bidIndex": 8, "address": "0xb560ff580aabb1c34491c2dd25f96ac127b09413", "y": 133, "x": 23, "updatedAt": "2017-12-23T02:17:14.448Z", "id": "23,133", "createdAt": "2017-12-15T22:00:47.961Z"}, {"projectId": null, "endsAt": "2017-12-25T04:48:35.667Z", "bidGroupId": 37221, "amount": "1563", "bidIndex": 29, "address": "0x38001a6ab8d70bab89333d9e945c847cbeb8c477", "y": 133, "x": 28, "updatedAt": "2017-12-23T22:48:35.784Z", "id": "28,133", "createdAt": "2017-12-15T22:00:51.974Z"}, {"projectId": null, "endsAt": "2017-12-27T13:38:12.941Z", "bidGroupId": 45167, "amount": "3818", "bidIndex": 0, "address": "0x38001a6ab8d70bab89333d9e945c847cbeb8c477", "y": 133, "x": 29, "updatedAt": "2017-12-26T07:38:13.000Z", "id": "29,133", "createdAt": "2017-12-15T22:00:52.786Z"}], "ok": true}